{
  "metadata": {
    "source_fichier": "C:\\Users\\dell\\OneDrive\\Bureau\\mexora_rh_lake\\offres_emploi_it_maroc.json",
    "date_ingestion": "2026-04-24T12:20:04.536115",
    "partition": "linkedin/2023_05",
    "nb_offres": 66
  },
  "offres": [
    {
      "id_offre": "LI-2023-00024",
      "source": "linkedin",
      "titre_poste": "Cloud Architect",
      "description": "Travail en mode Agile (Scrum/Kanban). Vous serez en charge de développer et maintenir nos applications. Mission : participer aux projets stratégiques de l'entreprise.",
      "competences_brut": "Java; React; NumPy; Azure; Scala; Spring Boot; Node.js",
      "entreprise": "IBM Maroc",
      "ville": "Casablanca",
      "type_contrat": "Freelance",
      "experience_requise": "",
      "salaire_brut": "2066-3861 EUR",
      "niveau_etudes": "Ingénieur",
      "secteur": "Énergie",
      "date_publication": "2023-05-26",
      "date_expiration": "2023-06-29",
      "nb_postes": 5,
      "teletravail": "Non",
      "langue_requise": [
        "Français"
      ]
    },
    {
      "id_offre": "LI-2023-00036",
      "source": "linkedin",
      "titre_poste": "Cloud Architect",
      "description": "Environnement technique moderne et innovant. Des connaissances en NumPy seraient un plus apprécié. Mission : participer aux projets stratégiques de l'entreprise. Vous serez en charge de développer et maintenir nos applications. Travail en mode Agile (Scrum/Kanban). Maîtrise de CI, CD; Looker; Spring Boot; NumPy; Django requise.",
      "competences_brut": "CI/CD; Looker; Spring Boot; NumPy; Django",
      "entreprise": "Informatique Services",
      "ville": "rabat",
      "type_contrat": "Freelance",
      "experience_requise": "1-2 ans",
      "salaire_brut": "36K DH",
      "niveau_etudes": null,
      "secteur": "Industrie",
      "date_publication": "2023-05-05",
      "date_expiration": "2023-05-02",
      "nb_postes": 2,
      "teletravail": "Hybride",
      "langue_requise": [
        "Anglais"
      ]
    },
    {
      "id_offre": "LI-2023-00152",
      "source": "linkedin",
      "titre_poste": "Data Scientist",
      "description": "Travail en mode Agile (Scrum/Kanban). Environnement technique moderne et innovant. Vous serez en charge de développer et maintenir nos applications. Mission : participer aux projets stratégiques de l'entreprise. Environnement technique : kafka.",
      "competences_brut": "Java\nDjango\nAngular\nLooker\nMachine Learning\nAzure\nKafka\nPower BI",
      "entreprise": "PwC",
      "ville": "FEZ",
      "type_contrat": "Permanent",
      "experience_requise": "",
      "salaire_brut": "30K DH",
      "niveau_etudes": "Master",
      "secteur": "Transport",
      "date_publication": "2023-05-23",
      "date_expiration": "2023-06-18",
      "nb_postes": 3,
      "teletravail": "",
      "langue_requise": [
        "Français"
      ]
    },
    {
      "id_offre": "LI-2023-00638",
      "source": "linkedin",
      "titre_poste": "Back-end Engineer",
      "description": "Environnement technique moderne et innovant. Vous serez en charge de développer et maintenir nos applications. Nous recherchons un(e) Back-end Engineer dynamique pour rejoindre notre équipe. Mission : participer aux projets stratégiques de l'entreprise. Travail en mode Agile (Scrum/Kanban).",
      "competences_brut": "Git / Django / Terraform",
      "entreprise": "Accenture",
      "ville": "Fès",
      "type_contrat": "Permanent",
      "experience_requise": "",
      "salaire_brut": "17051-28809 MAD",
      "niveau_etudes": "Master",
      "secteur": "Informatique / Télécom",
      "date_publication": "2023-05-14",
      "date_expiration": "2023-06-04",
      "nb_postes": 3,
      "teletravail": "Hybride",
      "langue_requise": [
        "Anglais",
        "Arabe"
      ]
    },
    {
      "id_offre": "LI-2023-00759",
      "source": "linkedin",
      "titre_poste": "Développeur Backend Junior",
      "description": "Mission : participer aux projets stratégiques de l'entreprise. Nous recherchons un(e) Développeur Backend Junior dynamique pour rejoindre notre équipe. Travail en mode Agile (Scrum/Kanban). Environnement technique : tableau. Vous serez en charge de développer et maintenir nos applications. Environnement technique moderne et innovant.",
      "competences_brut": "Deep Learning\nC#\nR\nMachine Learning",
      "entreprise": "HPS",
      "ville": "TANGER",
      "type_contrat": "cdi",
      "experience_requise": "1-2 ans",
      "salaire_brut": "Selon profil",
      "niveau_etudes": "Bac+4",
      "secteur": "E-commerce",
      "date_publication": "2023-05-31",
      "date_expiration": "2023-07-04",
      "nb_postes": 3,
      "teletravail": "",
      "langue_requise": [
        "Anglais",
        "Arabe"
      ]
    },
    {
      "id_offre": "LI-2023-00818",
      "source": "linkedin",
      "titre_poste": "Data Analyst",
      "description": "Maîtrise de Docker; R; Scikit-learn; Pandas; Kubernetes; GCP; Spring Boot requise. Travail en mode Agile (Scrum/Kanban). Des connaissances en Scikit-learn seraient un plus apprécié. Environnement technique moderne et innovant.",
      "competences_brut": "Docker; R; Scikit-learn; Pandas; Kubernetes; GCP; Spring Boot",
      "entreprise": "Accenture",
      "ville": "Rabat",
      "type_contrat": "Stage",
      "experience_requise": "",
      "salaire_brut": "10073-42226 MAD",
      "niveau_etudes": "Bac+2",
      "secteur": "Banque / Finance",
      "date_publication": "2023-05-21",
      "date_expiration": "2023-06-30",
      "nb_postes": 3,
      "teletravail": "Télétravail complet",
      "langue_requise": [
        "Anglais",
        "Arabe"
      ]
    },
    {
      "id_offre": "LI-2023-00845",
      "source": "linkedin",
      "titre_poste": "Data Engineer Senior",
      "description": "Mission : participer aux projets stratégiques de l'entreprise. Nous recherchons un(e) Data Engineer Senior dynamique pour rejoindre notre équipe. Environnement technique moderne et innovant. Travail en mode Agile (Scrum/Kanban). Maîtrise de Spark; Vue.js; Scikit-learn requise. Vous serez en charge de développer et maintenir nos applications.",
      "competences_brut": "Spark; Vue.js; Scikit-learn",
      "entreprise": "Informatique Services",
      "ville": "tanger",
      "type_contrat": "CDD",
      "experience_requise": "",
      "salaire_brut": null,
      "niveau_etudes": null,
      "secteur": "Santé",
      "date_publication": "2023-05-18",
      "date_expiration": "2023-06-10",
      "nb_postes": 3,
      "teletravail": "Non",
      "langue_requise": [
        "Français"
      ]
    },
    {
      "id_offre": "LI-2023-00898",
      "source": "linkedin",
      "titre_poste": "Cloud Architect Junior",
      "description": "Nous recherchons un(e) Cloud Architect Junior dynamique pour rejoindre notre équipe. Environnement technique : google cloud. Des connaissances en PyTorch seraient un plus apprécié. Travail en mode Agile (Scrum/Kanban).",
      "competences_brut": "Machine Learning • NLP • Terraform",
      "entreprise": "Attijariwafa",
      "ville": "FEZ",
      "type_contrat": "CDI",
      "experience_requise": null,
      "salaire_brut": null,
      "niveau_etudes": "Bac+3",
      "secteur": "Santé",
      "date_publication": "2023-05-14",
      "date_expiration": "2023-06-06",
      "nb_postes": 2,
      "teletravail": "Oui",
      "langue_requise": [
        "Anglais",
        "Arabe"
      ]
    },
    {
      "id_offre": "LI-2023-01095",
      "source": "linkedin",
      "titre_poste": "Data Eng. Senior",
      "description": "Vous serez en charge de développer et maintenir nos applications. Travail en mode Agile (Scrum/Kanban). Nous recherchons un(e) Data Eng. Senior dynamique pour rejoindre notre équipe. Maîtrise de AWS, Docker requise. Mission : participer aux projets stratégiques de l'entreprise.",
      "competences_brut": "Node.js / Docker / SQL / GCP / AWS / Scikit-learn / Scala / CI/CD",
      "entreprise": "Deloitte",
      "ville": "Fès",
      "type_contrat": "cdi",
      "experience_requise": "min 3 ans",
      "salaire_brut": "19595-34713 MAD",
      "niveau_etudes": null,
      "secteur": "E-commerce",
      "date_publication": "2023-05-16",
      "date_expiration": "2023-06-08",
      "nb_postes": 5,
      "teletravail": "Non",
      "langue_requise": [
        "Anglais",
        "Arabe"
      ]
    },
    {
      "id_offre": "LI-2023-01245",
      "source": "linkedin",
      "titre_poste": "Scrum Master",
      "description": "Travail en mode Agile (Scrum/Kanban). Nous recherchons un(e) Scrum Master dynamique pour rejoindre notre équipe. Maîtrise de Docker; React; Tableau; JavaScript requise. Environnement technique moderne et innovant. Mission : participer aux projets stratégiques de l'entreprise. Vous serez en charge de développer et maintenir nos applications.",
      "competences_brut": "Docker; React; Tableau; JavaScript",
      "entreprise": "IBM Maroc",
      "ville": "Casablanca",
      "type_contrat": "Stage",
      "experience_requise": "Débutant accepté",
      "salaire_brut": null,
      "niveau_etudes": null,
      "secteur": "Banque / Finance",
      "date_publication": "2023-05-07",
      "date_expiration": "2023-06-10",
      "nb_postes": 4,
      "teletravail": "",
      "langue_requise": []
    },
    {
      "id_offre": "LI-2023-01354",
      "source": "linkedin",
      "titre_poste": "Dev Data Senior",
      "description": "Maîtrise de Node.js, Vue.js requise. Travail en mode Agile (Scrum/Kanban). Des connaissances en TensorFlow seraient un plus apprécié. Mission : participer aux projets stratégiques de l'entreprise.",
      "competences_brut": "Vue.js / Looker / Deep Learning / Pandas / Power BI / JavaScript / Angular / Node.js",
      "entreprise": "KPMG",
      "ville": "Fès",
      "type_contrat": "Permanent",
      "experience_requise": "1-2 ans",
      "salaire_brut": "3913-7532 EUR",
      "niveau_etudes": "Bac+5",
      "secteur": "Énergie",
      "date_publication": "2023-05-03",
      "date_expiration": "2023-05-23",
      "nb_postes": 3,
      "teletravail": "Non",
      "langue_requise": []
    },
    {
      "id_offre": "LI-2023-01376",
      "source": "linkedin",
      "titre_poste": "Admin Systèmes Senior",
      "description": "Environnement technique moderne et innovant. Vous serez en charge de développer et maintenir nos applications. Des connaissances en NLP seraient un plus apprécié. Environnement technique : angular.",
      "competences_brut": "Airflow; Power BI; Kubernetes",
      "entreprise": "Deloitte",
      "ville": "Casablanca",
      "type_contrat": "CDI",
      "experience_requise": "",
      "salaire_brut": "10948-38379 MAD",
      "niveau_etudes": "Bac+4",
      "secteur": "Conseil",
      "date_publication": "2023-05-16",
      "date_expiration": "2023-06-19",
      "nb_postes": 3,
      "teletravail": "",
      "langue_requise": []
    },
    {
      "id_offre": "LI-2023-01469",
      "source": "linkedin",
      "titre_poste": "Chef de Projet IT",
      "description": "Mission : participer aux projets stratégiques de l'entreprise. Travail en mode Agile (Scrum/Kanban). Nous recherchons un(e) Chef de Projet IT dynamique pour rejoindre notre équipe. Environnement technique moderne et innovant. Vous serez en charge de développer et maintenir nos applications.",
      "competences_brut": "Azure\nTableau\nGCP\nJava\nDeep Learning\nDocker\nJenkins",
      "entreprise": "Attijariwafa",
      "ville": "Rabat",
      "type_contrat": "Contrat à durée indéterminée",
      "experience_requise": "min 3 ans",
      "salaire_brut": "39K DH",
      "niveau_etudes": null,
      "secteur": "Transport",
      "date_publication": "2023-05-20",
      "date_expiration": "2023-07-04",
      "nb_postes": 3,
      "teletravail": "Non",
      "langue_requise": [
        "Français",
        "Anglais"
      ]
    },
    {
      "id_offre": "LI-2023-01596",
      "source": "linkedin",
      "titre_poste": "BI Developer Senior",
      "description": "Maîtrise de Spring Boot; Django; Looker requise. Environnement technique moderne et innovant. Nous recherchons un(e) BI Developer Senior dynamique pour rejoindre notre équipe. Travail en mode Agile (Scrum/Kanban). Vous serez en charge de développer et maintenir nos applications. Mission : participer aux projets stratégiques de l'entreprise.",
      "competences_brut": "Spring Boot; Django; Looker",
      "entreprise": "Capgemini",
      "ville": "CASABLANCA",
      "type_contrat": "Permanent",
      "experience_requise": "5+ ans",
      "salaire_brut": "14345-45497 MAD",
      "niveau_etudes": "Bac+5",
      "secteur": "Banque / Finance",
      "date_publication": "2023-05-19",
      "date_expiration": "2023-06-18",
      "nb_postes": 1,
      "teletravail": "Partiel",
      "langue_requise": [
        "Français",
        "Anglais"
      ]
    },
    {
      "id_offre": "LI-2023-01614",
      "source": "linkedin",
      "titre_poste": "Développeur Full Stack Junior",
      "description": "Environnement technique moderne et innovant. Mission : participer aux projets stratégiques de l'entreprise. Vous serez en charge de développer et maintenir nos applications. Travail en mode Agile (Scrum/Kanban). Maîtrise de Azure, Scikit-learn requise. Environnement technique : node.",
      "competences_brut": "Azure / Power BI / Scikit-learn / Airflow / Machine Learning / Java / TensorFlow / Git",
      "entreprise": "IBM Maroc",
      "ville": "TANGER",
      "type_contrat": "CDI",
      "experience_requise": "Senior (7+ ans)",
      "salaire_brut": "9K-35K MAD",
      "niveau_etudes": "Master",
      "secteur": "Informatique / Télécom",
      "date_publication": "2023-05-12",
      "date_expiration": "2023-06-11",
      "nb_postes": 3,
      "teletravail": "",
      "langue_requise": []
    },
    {
      "id_offre": "LI-2023-01642",
      "source": "linkedin",
      "titre_poste": "Cloud Architect",
      "description": "Maîtrise de CD, Pandas requise. Mission : participer aux projets stratégiques de l'entreprise. Nous recherchons un(e) Cloud Architect dynamique pour rejoindre notre équipe. Environnement technique moderne et innovant. Vous serez en charge de développer et maintenir nos applications.",
      "competences_brut": "GCP\nCI/CD\nPython\nJava\nPandas",
      "entreprise": "Orange Maroc",
      "ville": "Casablanca",
      "type_contrat": "Permanent",
      "experience_requise": "",
      "salaire_brut": "37K DH",
      "niveau_etudes": null,
      "secteur": "Transport",
      "date_publication": "2023-05-31",
      "date_expiration": "2023-07-07",
      "nb_postes": 2,
      "teletravail": "Hybride",
      "langue_requise": [
        "Français",
        "Anglais"
      ]
    },
    {
      "id_offre": "LI-2023-01696",
      "source": "linkedin",
      "titre_poste": "Data Engineer",
      "description": "Des connaissances en R seraient un plus apprécié. Environnement technique moderne et innovant. Nous recherchons un(e) Data Engineer dynamique pour rejoindre notre équipe.",
      "competences_brut": "Deep Learning • Terraform • PyTorch • Machine Learning",
      "entreprise": "CloudMaroc",
      "ville": "Casa",
      "type_contrat": "Permanent",
      "experience_requise": "1-2 ans",
      "salaire_brut": null,
      "niveau_etudes": "Bac+2",
      "secteur": "Industrie",
      "date_publication": "2023-05-05",
      "date_expiration": "2023-04-26",
      "nb_postes": 4,
      "teletravail": "Non",
      "langue_requise": [
        "Français",
        "Anglais"
      ]
    },
    {
      "id_offre": "LI-2023-01719",
      "source": "linkedin",
      "titre_poste": "Chef de Projet IT",
      "description": "Travail en mode Agile (Scrum/Kanban). Maîtrise de Git, PyTorch requise. Mission : participer aux projets stratégiques de l'entreprise. Nous recherchons un(e) Chef de Projet IT dynamique pour rejoindre notre équipe.",
      "competences_brut": "Git\nJenkins\nNumPy\nNLP\nPyTorch\nScala\nTableau\nAzure",
      "entreprise": "Capgemini",
      "ville": "Fès",
      "type_contrat": "Freelance",
      "experience_requise": "",
      "salaire_brut": "14792-17856 MAD",
      "niveau_etudes": "Ingénieur",
      "secteur": "E-commerce",
      "date_publication": "2023-05-18",
      "date_expiration": "2023-06-09",
      "nb_postes": 3,
      "teletravail": "Non",
      "langue_requise": [
        "Anglais"
      ]
    },
    {
      "id_offre": "LI-2023-01757",
      "source": "linkedin",
      "titre_poste": "Back-end Engineer",
      "description": "Environnement technique moderne et innovant. Nous recherchons un(e) Back-end Engineer dynamique pour rejoindre notre équipe. Mission : participer aux projets stratégiques de l'entreprise.",
      "competences_brut": "JavaScript / Power BI / CI/CD / Vue.js",
      "entreprise": "Microsoft Maroc",
      "ville": "Rabat",
      "type_contrat": "Permanent",
      "experience_requise": "1-2 ans",
      "salaire_brut": "3876-6313 EUR",
      "niveau_etudes": "Bac+5",
      "secteur": "Énergie",
      "date_publication": "2023-05-17",
      "date_expiration": "2023-06-23",
      "nb_postes": 4,
      "teletravail": "Partiel",
      "langue_requise": [
        "Français",
        "Anglais"
      ]
    },
    {
      "id_offre": "LI-2023-01854",
      "source": "linkedin",
      "titre_poste": "Devops Engineer Lead",
      "description": "Vous serez en charge de développer et maintenir nos applications. Des connaissances en NLP seraient un plus apprécié. Travail en mode Agile (Scrum/Kanban).",
      "competences_brut": "React / SQL / Git / Django / Docker / CI/CD / Python",
      "entreprise": "Oracle Maroc",
      "ville": "rabat",
      "type_contrat": "Stage",
      "experience_requise": "5+ ans",
      "salaire_brut": "2854-6307 EUR",
      "niveau_etudes": "Bac+4",
      "secteur": "Informatique / Télécom",
      "date_publication": "2023-05-15",
      "date_expiration": "2023-06-18",
      "nb_postes": 2,
      "teletravail": "",
      "langue_requise": [
        "Français"
      ]
    },
    {
      "id_offre": "LI-2023-01896",
      "source": "linkedin",
      "titre_poste": "Dev Full Stack",
      "description": "Maîtrise de SQL, Pandas requise. Environnement technique moderne et innovant. Vous serez en charge de développer et maintenir nos applications. Environnement technique : reactjs.",
      "competences_brut": "Hadoop / SQL / R / Pandas / Airflow / PyTorch",
      "entreprise": "Capgemini",
      "ville": "RABAT",
      "type_contrat": "CDD",
      "experience_requise": "Moins de 1 an",
      "salaire_brut": "25K-29K MAD",
      "niveau_etudes": "Licence",
      "secteur": "E-commerce",
      "date_publication": "2023-05-03",
      "date_expiration": "2023-06-10",
      "nb_postes": 3,
      "teletravail": "Non",
      "langue_requise": [
        "Anglais",
        "Arabe"
      ]
    },
    {
      "id_offre": "LI-2023-01905",
      "source": "linkedin",
      "titre_poste": "Back-end Engineer",
      "description": "Mission : participer aux projets stratégiques de l'entreprise. Environnement technique moderne et innovant. Travail en mode Agile (Scrum/Kanban). Des connaissances en Looker seraient un plus apprécié. Nous recherchons un(e) Back-end Engineer dynamique pour rejoindre notre équipe. Maîtrise de Kubernetes, Spring Boot requise.",
      "competences_brut": "Scikit-learn, Angular, Kubernetes, Scala, Spring Boot, Spark",
      "entreprise": "HPS",
      "ville": "CASABLANCA",
      "type_contrat": "Permanent",
      "experience_requise": "min 3 ans",
      "salaire_brut": null,
      "niveau_etudes": "Bac+5",
      "secteur": "Banque / Finance",
      "date_publication": "2023-05-01",
      "date_expiration": "2023-06-15",
      "nb_postes": 4,
      "teletravail": "",
      "langue_requise": [
        "Français",
        "Anglais"
      ]
    },
    {
      "id_offre": "LI-2023-02039",
      "source": "linkedin",
      "titre_poste": "Scrum Master",
      "description": "Travail en mode Agile (Scrum/Kanban). Mission : participer aux projets stratégiques de l'entreprise. Vous serez en charge de développer et maintenir nos applications. Nous recherchons un(e) Scrum Master dynamique pour rejoindre notre équipe. Environnement technique moderne et innovant.",
      "competences_brut": "C#\nMachine Learning\nDjango\nGit\nScala",
      "entreprise": "Solutions IT",
      "ville": "Casablanca",
      "type_contrat": "cdi",
      "experience_requise": null,
      "salaire_brut": "À définir",
      "niveau_etudes": "Bac+3",
      "secteur": "Informatique / Télécom",
      "date_publication": "2023-05-14",
      "date_expiration": "2023-06-25",
      "nb_postes": 3,
      "teletravail": "Partiel",
      "langue_requise": [
        "Anglais",
        "Arabe"
      ]
    },
    {
      "id_offre": "LI-2023-02047",
      "source": "linkedin",
      "titre_poste": "Scrum Master Senior",
      "description": "Mission : participer aux projets stratégiques de l'entreprise. Environnement technique moderne et innovant. Des connaissances en Java seraient un plus apprécié. Vous serez en charge de développer et maintenir nos applications. Nous recherchons un(e) Scrum Master Senior dynamique pour rejoindre notre équipe. Maîtrise de SQL; Machine Learning; PyTorch; Tableau; Pandas; TensorFlow; Scikit-learn; Jenkins requise.",
      "competences_brut": "SQL; Machine Learning; PyTorch; Tableau; Pandas; TensorFlow; Scikit-learn; Jenkins",
      "entreprise": "TechMaroc SARL",
      "ville": "tanger",
      "type_contrat": "Stage",
      "experience_requise": "1-2 ans",
      "salaire_brut": null,
      "niveau_etudes": "Bac+3",
      "secteur": "Transport",
      "date_publication": "2023-05-26",
      "date_expiration": "2023-07-03",
      "nb_postes": 4,
      "teletravail": "",
      "langue_requise": [
        "Français"
      ]
    },
    {
      "id_offre": "LI-2023-02179",
      "source": "linkedin",
      "titre_poste": "Développeur Backend",
      "description": "Travail en mode Agile (Scrum/Kanban). Environnement technique moderne et innovant. Mission : participer aux projets stratégiques de l'entreprise. Maîtrise de Spark, Machine Learning requise.",
      "competences_brut": "Machine Learning • Looker • Spark",
      "entreprise": "Accenture",
      "ville": "Casablanca",
      "type_contrat": "Freelance",
      "experience_requise": "Senior (7+ ans)",
      "salaire_brut": "4087-5273 EUR",
      "niveau_etudes": "Bac+2",
      "secteur": "Industrie",
      "date_publication": "2023-05-05",
      "date_expiration": "2023-06-01",
      "nb_postes": 2,
      "teletravail": "Oui",
      "langue_requise": [
        "Anglais"
      ]
    },
    {
      "id_offre": "LI-2023-02303",
      "source": "linkedin",
      "titre_poste": "Scientifique des données",
      "description": "Maîtrise de PyTorch, JavaScript requise. Travail en mode Agile (Scrum/Kanban). Mission : participer aux projets stratégiques de l'entreprise. Nous recherchons un(e) Scientifique des données dynamique pour rejoindre notre équipe. Vous serez en charge de développer et maintenir nos applications. Environnement technique moderne et innovant.",
      "competences_brut": "JavaScript • Looker • Pandas • PyTorch",
      "entreprise": "KPMG",
      "ville": "tanger",
      "type_contrat": "cdi",
      "experience_requise": "Moins de 1 an",
      "salaire_brut": "18594-28196 MAD",
      "niveau_etudes": null,
      "secteur": "Conseil",
      "date_publication": "2023-05-12",
      "date_expiration": "2023-06-02",
      "nb_postes": 3,
      "teletravail": "Partiel",
      "langue_requise": []
    },
    {
      "id_offre": "LI-2023-02347",
      "source": "linkedin",
      "titre_poste": "Analyste Data",
      "description": "Mission : participer aux projets stratégiques de l'entreprise. Vous serez en charge de développer et maintenir nos applications. Maîtrise de R, JavaScript requise. Environnement technique : java8.",
      "competences_brut": "Scala • CI/CD • Angular • Node.js • JavaScript • R • Tableau",
      "entreprise": "Maroc Telecom",
      "ville": "rabat",
      "type_contrat": "CDD",
      "experience_requise": "3-5 ans",
      "salaire_brut": "23K-28K MAD",
      "niveau_etudes": "Bac+2",
      "secteur": "E-commerce",
      "date_publication": "2023-05-07",
      "date_expiration": "2023-05-27",
      "nb_postes": 4,
      "teletravail": "Non",
      "langue_requise": [
        "Français",
        "Anglais"
      ]
    },
    {
      "id_offre": "LI-2023-02381",
      "source": "linkedin",
      "titre_poste": "Data Engineer Junior",
      "description": "Vous serez en charge de développer et maintenir nos applications. Travail en mode Agile (Scrum/Kanban). Nous recherchons un(e) Data Engineer Junior dynamique pour rejoindre notre équipe.",
      "competences_brut": "Tableau; React",
      "entreprise": "Solutions IT",
      "ville": "Tanger",
      "type_contrat": "Freelance",
      "experience_requise": null,
      "salaire_brut": "19K DH",
      "niveau_etudes": "Bac+2",
      "secteur": "Industrie",
      "date_publication": "2023-05-26",
      "date_expiration": "2023-06-24",
      "nb_postes": 1,
      "teletravail": "Oui",
      "langue_requise": [
        "Français",
        "Anglais"
      ]
    },
    {
      "id_offre": "LI-2023-02447",
      "source": "linkedin",
      "titre_poste": "Data Scientist",
      "description": "Nous recherchons un(e) Data Scientist dynamique pour rejoindre notre équipe. Maîtrise de Hadoop, SQL requise. Environnement technique moderne et innovant. Travail en mode Agile (Scrum/Kanban). Mission : participer aux projets stratégiques de l'entreprise. Des connaissances en Power BI seraient un plus apprécié.",
      "competences_brut": "Hadoop\nPyTorch\nSQL\nScala",
      "entreprise": "Wafasalaf",
      "ville": "MARRAKECH",
      "type_contrat": "Permanent",
      "experience_requise": "3 à 5 ans",
      "salaire_brut": "À définir",
      "niveau_etudes": "Bac+3",
      "secteur": "Industrie",
      "date_publication": "2023-05-24",
      "date_expiration": "2023-06-20",
      "nb_postes": 3,
      "teletravail": "Hybride",
      "langue_requise": [
        "Français",
        "Anglais"
      ]
    },
    {
      "id_offre": "LI-2023-02456",
      "source": "linkedin",
      "titre_poste": "Machine Learning Engineer",
      "description": "Environnement technique : looker. Nous recherchons un(e) Machine Learning Engineer dynamique pour rejoindre notre équipe. Environnement technique moderne et innovant. Travail en mode Agile (Scrum/Kanban). Vous serez en charge de développer et maintenir nos applications. Mission : participer aux projets stratégiques de l'entreprise.",
      "competences_brut": "SQL / Deep Learning / Scala / Vue.js / Kafka / Git / NLP / Machine Learning",
      "entreprise": "CloudMaroc",
      "ville": "Casablanca",
      "type_contrat": "Contrat à durée indéterminée",
      "experience_requise": null,
      "salaire_brut": null,
      "niveau_etudes": "Bac+3",
      "secteur": "Conseil",
      "date_publication": "2023-05-01",
      "date_expiration": "2023-05-26",
      "nb_postes": 2,
      "teletravail": "Partiel",
      "langue_requise": [
        "Français",
        "Anglais"
      ]
    },
    {
      "id_offre": "LI-2023-02555",
      "source": "linkedin",
      "titre_poste": "Data Engineer Junior",
      "description": "Des connaissances en Git seraient un plus apprécié. Vous serez en charge de développer et maintenir nos applications. Travail en mode Agile (Scrum/Kanban).",
      "competences_brut": "Terraform / NumPy / Looker / Java / NLP / PyTorch",
      "entreprise": "Accenture",
      "ville": "casa",
      "type_contrat": "CDD",
      "experience_requise": "Moins de 1 an",
      "salaire_brut": "16K-26K MAD",
      "niveau_etudes": "Licence",
      "secteur": "E-commerce",
      "date_publication": "2023-05-12",
      "date_expiration": "2023-06-07",
      "nb_postes": 1,
      "teletravail": "Télétravail complet",
      "langue_requise": [
        "Français"
      ]
    },
    {
      "id_offre": "LI-2023-02607",
      "source": "linkedin",
      "titre_poste": "Data Engineer",
      "description": "Environnement technique moderne et innovant. Vous serez en charge de développer et maintenir nos applications. Nous recherchons un(e) Data Engineer dynamique pour rejoindre notre équipe. Des connaissances en Python seraient un plus apprécié.",
      "competences_brut": "Power BI • Looker • Deep Learning",
      "entreprise": "Orange Maroc",
      "ville": "tanger",
      "type_contrat": "Freelance",
      "experience_requise": null,
      "salaire_brut": "Selon profil",
      "niveau_etudes": "Ingénieur",
      "secteur": "E-commerce",
      "date_publication": "2023-05-25",
      "date_expiration": "2023-07-05",
      "nb_postes": 3,
      "teletravail": "",
      "langue_requise": [
        "Anglais",
        "Arabe"
      ]
    },
    {
      "id_offre": "LI-2023-02732",
      "source": "linkedin",
      "titre_poste": "BI Developer",
      "description": "Environnement technique moderne et innovant. Maîtrise de PyTorch, Pandas requise. Vous serez en charge de développer et maintenir nos applications. Travail en mode Agile (Scrum/Kanban). Mission : participer aux projets stratégiques de l'entreprise.",
      "competences_brut": "Pandas • Azure • AWS • PyTorch • Angular • Power BI • Machine Learning",
      "entreprise": "Capgemini",
      "ville": "CASABLANCA",
      "type_contrat": "Permanent",
      "experience_requise": "5+ ans",
      "salaire_brut": "2348-7250 EUR",
      "niveau_etudes": "Bac+2",
      "secteur": "Santé",
      "date_publication": "2023-05-27",
      "date_expiration": "2023-06-24",
      "nb_postes": 3,
      "teletravail": "Hybride",
      "langue_requise": [
        "Anglais"
      ]
    },
    {
      "id_offre": "LI-2023-02896",
      "source": "linkedin",
      "titre_poste": "Développeur Backend",
      "description": "Environnement technique moderne et innovant. Nous recherchons un(e) Développeur Backend dynamique pour rejoindre notre équipe. Travail en mode Agile (Scrum/Kanban). Environnement technique : react. Mission : participer aux projets stratégiques de l'entreprise.",
      "competences_brut": "JavaScript / Kafka",
      "entreprise": "Orange Maroc",
      "ville": "rabat",
      "type_contrat": "cdi",
      "experience_requise": null,
      "salaire_brut": "À définir",
      "niveau_etudes": "Licence",
      "secteur": "Conseil",
      "date_publication": "2023-05-08",
      "date_expiration": "2023-05-29",
      "nb_postes": 5,
      "teletravail": "Hybride",
      "langue_requise": [
        "Français",
        "Anglais"
      ]
    },
    {
      "id_offre": "LI-2023-02909",
      "source": "linkedin",
      "titre_poste": "Data Engineer",
      "description": "Des connaissances en Terraform seraient un plus apprécié. Vous serez en charge de développer et maintenir nos applications. Nous recherchons un(e) Data Engineer dynamique pour rejoindre notre équipe. Travail en mode Agile (Scrum/Kanban). Mission : participer aux projets stratégiques de l'entreprise.",
      "competences_brut": "Django; SQL; NumPy; Tableau; Git; Hadoop; JavaScript; Spark",
      "entreprise": "KPMG",
      "ville": "RABAT",
      "type_contrat": "cdi",
      "experience_requise": "Débutant accepté",
      "salaire_brut": "10K DH",
      "niveau_etudes": "Bac+2",
      "secteur": "Industrie",
      "date_publication": "2023-05-21",
      "date_expiration": "2023-06-25",
      "nb_postes": 4,
      "teletravail": "Partiel",
      "langue_requise": [
        "Anglais",
        "Arabe"
      ]
    },
    {
      "id_offre": "LI-2023-03015",
      "source": "linkedin",
      "titre_poste": "Admin Systèmes",
      "description": "Environnement technique : spring. Vous serez en charge de développer et maintenir nos applications. Environnement technique moderne et innovant. Maîtrise de Git, Vue.js requise.",
      "competences_brut": "Git / Scala / Vue.js / React / Docker",
      "entreprise": "Accenture",
      "ville": "Casablanca",
      "type_contrat": "Freelance",
      "experience_requise": "1-2 ans",
      "salaire_brut": "18K DH",
      "niveau_etudes": "Ingénieur",
      "secteur": "E-commerce",
      "date_publication": "2023-05-19",
      "date_expiration": "2023-06-18",
      "nb_postes": 4,
      "teletravail": "Non",
      "langue_requise": []
    },
    {
      "id_offre": "LI-2023-03083",
      "source": "linkedin",
      "titre_poste": "Data Analyst Senior",
      "description": "Vous serez en charge de développer et maintenir nos applications. Nous recherchons un(e) Data Analyst Senior dynamique pour rejoindre notre équipe. Environnement technique moderne et innovant. Mission : participer aux projets stratégiques de l'entreprise.",
      "competences_brut": "Tableau / R / Git / Jenkins / Looker / C# / PyTorch",
      "entreprise": "CGI Maroc",
      "ville": "Casa",
      "type_contrat": "Freelance",
      "experience_requise": "Débutant accepté",
      "salaire_brut": "4028-6760 EUR",
      "niveau_etudes": "Bac+3",
      "secteur": "Conseil",
      "date_publication": "2023-05-03",
      "date_expiration": "2023-06-13",
      "nb_postes": 3,
      "teletravail": "",
      "langue_requise": [
        "Français",
        "Anglais"
      ]
    },
    {
      "id_offre": "LI-2023-03269",
      "source": "linkedin",
      "titre_poste": "Data Engineer Junior",
      "description": "Environnement technique moderne et innovant. Des connaissances en Docker seraient un plus apprécié. Environnement technique : lambda.",
      "competences_brut": "Airflow\nHadoop\nNLP",
      "entreprise": "Microsoft Maroc",
      "ville": "Casablanca",
      "type_contrat": "cdi",
      "experience_requise": "",
      "salaire_brut": "14341-48531 MAD",
      "niveau_etudes": null,
      "secteur": "Informatique / Télécom",
      "date_publication": "2023-05-06",
      "date_expiration": "2023-06-07",
      "nb_postes": 1,
      "teletravail": "Hybride",
      "langue_requise": []
    },
    {
      "id_offre": "LI-2023-03359",
      "source": "linkedin",
      "titre_poste": "Chef de Projet IT Senior",
      "description": "Mission : participer aux projets stratégiques de l'entreprise. Nous recherchons un(e) Chef de Projet IT Senior dynamique pour rejoindre notre équipe. Vous serez en charge de développer et maintenir nos applications. Travail en mode Agile (Scrum/Kanban). Environnement technique moderne et innovant.",
      "competences_brut": "PyTorch; Machine Learning",
      "entreprise": "Deloitte",
      "ville": "Rabat",
      "type_contrat": "CDD",
      "experience_requise": "3 à 5 ans",
      "salaire_brut": "Confidentiel",
      "niveau_etudes": "Master",
      "secteur": "Informatique / Télécom",
      "date_publication": "2023-05-05",
      "date_expiration": "2023-05-26",
      "nb_postes": 1,
      "teletravail": "Non",
      "langue_requise": [
        "Anglais",
        "Arabe"
      ]
    },
    {
      "id_offre": "LI-2023-03403",
      "source": "linkedin",
      "titre_poste": "Data Engineer",
      "description": "Environnement technique moderne et innovant. Mission : participer aux projets stratégiques de l'entreprise. Vous serez en charge de développer et maintenir nos applications. Travail en mode Agile (Scrum/Kanban). Nous recherchons un(e) Data Engineer dynamique pour rejoindre notre équipe. Environnement technique : kafka.",
      "competences_brut": "Tableau, Java, Spark, Pandas",
      "entreprise": "DataSmart",
      "ville": "TANGER",
      "type_contrat": "CDD",
      "experience_requise": "5+ ans",
      "salaire_brut": "2067-4294 EUR",
      "niveau_etudes": null,
      "secteur": "Conseil",
      "date_publication": "2023-05-19",
      "date_expiration": "2023-06-18",
      "nb_postes": 1,
      "teletravail": "Partiel",
      "langue_requise": []
    },
    {
      "id_offre": "LI-2023-03516",
      "source": "linkedin",
      "titre_poste": "Data Scientist",
      "description": "Mission : participer aux projets stratégiques de l'entreprise. Des connaissances en PyTorch seraient un plus apprécié. Travail en mode Agile (Scrum/Kanban). Environnement technique : ec2. Nous recherchons un(e) Data Scientist dynamique pour rejoindre notre équipe. Vous serez en charge de développer et maintenir nos applications.",
      "competences_brut": "Spark, Machine Learning, TensorFlow, Spring Boot, Scikit-learn, Azure, C#",
      "entreprise": "IBM Maroc",
      "ville": "Meknès",
      "type_contrat": "Permanent",
      "experience_requise": "Débutant accepté",
      "salaire_brut": "19501-49476 MAD",
      "niveau_etudes": null,
      "secteur": "Transport",
      "date_publication": "2023-05-10",
      "date_expiration": "2023-06-19",
      "nb_postes": 3,
      "teletravail": "",
      "langue_requise": [
        "Anglais",
        "Arabe"
      ]
    },
    {
      "id_offre": "LI-2023-03566",
      "source": "linkedin",
      "titre_poste": "Data Analyst Junior",
      "description": "Travail en mode Agile (Scrum/Kanban). Mission : participer aux projets stratégiques de l'entreprise. Environnement technique moderne et innovant. Vous serez en charge de développer et maintenir nos applications.",
      "competences_brut": "Node.js\nJava\nKubernetes\nSpring Boot",
      "entreprise": "M2M Group",
      "ville": "Casa",
      "type_contrat": "Contrat à durée indéterminée",
      "experience_requise": null,
      "salaire_brut": "11K-20K MAD",
      "niveau_etudes": null,
      "secteur": "Santé",
      "date_publication": "2023-05-16",
      "date_expiration": "2023-06-16",
      "nb_postes": 5,
      "teletravail": "",
      "langue_requise": [
        "Français"
      ]
    },
    {
      "id_offre": "LI-2023-03598",
      "source": "linkedin",
      "titre_poste": "Data Eng. Lead",
      "description": "Environnement technique : reactjs. Mission : participer aux projets stratégiques de l'entreprise. Nous recherchons un(e) Data Eng. Lead dynamique pour rejoindre notre équipe. Vous serez en charge de développer et maintenir nos applications. Travail en mode Agile (Scrum/Kanban).",
      "competences_brut": "Hadoop, PyTorch, NumPy, Java, Node.js, Spark, Angular, Kubernetes",
      "entreprise": "DataSmart",
      "ville": "rabat",
      "type_contrat": "cdi",
      "experience_requise": "3-5 ans",
      "salaire_brut": "22K DH",
      "niveau_etudes": "Bac+3",
      "secteur": "E-commerce",
      "date_publication": "2023-05-27",
      "date_expiration": "2023-07-11",
      "nb_postes": 2,
      "teletravail": "",
      "langue_requise": [
        "Anglais"
      ]
    },
    {
      "id_offre": "LI-2023-03659",
      "source": "linkedin",
      "titre_poste": "Ingénieur Big Data",
      "description": "Mission : participer aux projets stratégiques de l'entreprise. Nous recherchons un(e) Ingénieur Big Data dynamique pour rejoindre notre équipe. Vous serez en charge de développer et maintenir nos applications. Des connaissances en Hadoop seraient un plus apprécié. Environnement technique : rlang. Maîtrise de Looker, Python requise.",
      "competences_brut": "Looker, Python",
      "entreprise": "Wafasalaf",
      "ville": "TANGER",
      "type_contrat": "CDD",
      "experience_requise": "Senior (7+ ans)",
      "salaire_brut": "25K-35K MAD",
      "niveau_etudes": null,
      "secteur": "Conseil",
      "date_publication": "2023-05-25",
      "date_expiration": "2023-06-25",
      "nb_postes": 3,
      "teletravail": "",
      "langue_requise": [
        "Français"
      ]
    },
    {
      "id_offre": "LI-2023-03673",
      "source": "linkedin",
      "titre_poste": "Data Analyst Junior",
      "description": "Vous serez en charge de développer et maintenir nos applications. Nous recherchons un(e) Data Analyst Junior dynamique pour rejoindre notre équipe. Mission : participer aux projets stratégiques de l'entreprise. Des connaissances en TensorFlow seraient un plus apprécié. Maîtrise de React, Azure requise.",
      "competences_brut": "Pandas, Java, Jenkins, React, Deep Learning, Angular, Azure, Hadoop",
      "entreprise": "KPMG",
      "ville": "rabat",
      "type_contrat": "Freelance",
      "experience_requise": "Débutant accepté",
      "salaire_brut": "42K DH",
      "niveau_etudes": "Ingénieur",
      "secteur": "Énergie",
      "date_publication": "2023-05-08",
      "date_expiration": "2023-06-07",
      "nb_postes": 2,
      "teletravail": "Télétravail complet",
      "langue_requise": [
        "Français",
        "Anglais"
      ]
    },
    {
      "id_offre": "LI-2023-03697",
      "source": "linkedin",
      "titre_poste": "Dev Data Junior",
      "description": "Environnement technique moderne et innovant. Des connaissances en React seraient un plus apprécié. Nous recherchons un(e) Dev Data Junior dynamique pour rejoindre notre équipe. Maîtrise de Tableau, Azure requise. Mission : participer aux projets stratégiques de l'entreprise. Vous serez en charge de développer et maintenir nos applications.",
      "competences_brut": "Scikit-learn, Tableau, Azure, Vue.js",
      "entreprise": "Inwi",
      "ville": "CASABLANCA",
      "type_contrat": "Freelance",
      "experience_requise": "Senior (7+ ans)",
      "salaire_brut": "À définir",
      "niveau_etudes": null,
      "secteur": "Énergie",
      "date_publication": "2023-05-10",
      "date_expiration": "2023-06-10",
      "nb_postes": 3,
      "teletravail": "Hybride",
      "langue_requise": [
        "Anglais"
      ]
    },
    {
      "id_offre": "LI-2023-03802",
      "source": "linkedin",
      "titre_poste": "Architecte Logiciel",
      "description": "Travail en mode Agile (Scrum/Kanban). Mission : participer aux projets stratégiques de l'entreprise. Maîtrise de Terraform, Power BI requise. Nous recherchons un(e) Architecte Logiciel dynamique pour rejoindre notre équipe. Environnement technique moderne et innovant.",
      "competences_brut": "Power BI\nGCP\nDeep Learning\nTerraform\nNumPy\nAzure",
      "entreprise": "Inwi",
      "ville": "Fès",
      "type_contrat": "CDD",
      "experience_requise": "",
      "salaire_brut": "4305-7336 EUR",
      "niveau_etudes": null,
      "secteur": "Informatique / Télécom",
      "date_publication": "2023-05-07",
      "date_expiration": "2023-05-29",
      "nb_postes": 4,
      "teletravail": "",
      "langue_requise": [
        "Français",
        "Anglais"
      ]
    },
    {
      "id_offre": "LI-2023-03814",
      "source": "linkedin",
      "titre_poste": "BI Developer",
      "description": "Vous serez en charge de développer et maintenir nos applications. Environnement technique moderne et innovant. Des connaissances en Spring Boot seraient un plus apprécié. Mission : participer aux projets stratégiques de l'entreprise. Maîtrise de Scikit-learn; Power BI; C#; SQL; Looker; Jenkins; Kafka; Docker requise. Travail en mode Agile (Scrum/Kanban).",
      "competences_brut": "Scikit-learn; Power BI; C#; SQL; Looker; Jenkins; Kafka; Docker",
      "entreprise": "IBM Maroc",
      "ville": "Fès",
      "type_contrat": "CDI",
      "experience_requise": "min 3 ans",
      "salaire_brut": "Négociable",
      "niveau_etudes": "Bac+4",
      "secteur": "Conseil",
      "date_publication": "2023-05-08",
      "date_expiration": "2023-06-01",
      "nb_postes": 3,
      "teletravail": "",
      "langue_requise": [
        "Anglais"
      ]
    },
    {
      "id_offre": "LI-2023-03835",
      "source": "linkedin",
      "titre_poste": "Architecte Logiciel",
      "description": "Environnement technique moderne et innovant. Mission : participer aux projets stratégiques de l'entreprise. Environnement technique : node.",
      "competences_brut": "Kubernetes • GCP • Jenkins • Terraform • Power BI • Node.js",
      "entreprise": "Banque Populaire",
      "ville": "Casa",
      "type_contrat": "Stage",
      "experience_requise": "Moins de 1 an",
      "salaire_brut": "14743-28713 MAD",
      "niveau_etudes": null,
      "secteur": "Banque / Finance",
      "date_publication": "2023-05-02",
      "date_expiration": "2023-04-25",
      "nb_postes": 2,
      "teletravail": "Non",
      "langue_requise": []
    },
    {
      "id_offre": "LI-2023-03856",
      "source": "linkedin",
      "titre_poste": "Chef de Projet IT",
      "description": "Mission : participer aux projets stratégiques de l'entreprise. Nous recherchons un(e) Chef de Projet IT dynamique pour rejoindre notre équipe. Vous serez en charge de développer et maintenir nos applications.",
      "competences_brut": "AWS / Vue.js / C# / Spark / CI/CD / R",
      "entreprise": "TechMaroc SARL",
      "ville": "Meknès",
      "type_contrat": "CDI",
      "experience_requise": null,
      "salaire_brut": "4184-5009 EUR",
      "niveau_etudes": "Ingénieur",
      "secteur": "Énergie",
      "date_publication": "2023-05-05",
      "date_expiration": "2023-06-09",
      "nb_postes": 4,
      "teletravail": "Non",
      "langue_requise": []
    },
    {
      "id_offre": "LI-2023-03916",
      "source": "linkedin",
      "titre_poste": "Machine Learning Engineer",
      "description": "Des connaissances en NumPy seraient un plus apprécié. Nous recherchons un(e) Machine Learning Engineer dynamique pour rejoindre notre équipe. Vous serez en charge de développer et maintenir nos applications.",
      "competences_brut": "GCP / React",
      "entreprise": "CGI Maroc",
      "ville": "Rabat",
      "type_contrat": "CDI",
      "experience_requise": "Débutant accepté",
      "salaire_brut": null,
      "niveau_etudes": "Master",
      "secteur": "Banque / Finance",
      "date_publication": "2023-05-05",
      "date_expiration": "2023-06-19",
      "nb_postes": 3,
      "teletravail": "Hybride",
      "langue_requise": [
        "Anglais",
        "Arabe"
      ]
    },
    {
      "id_offre": "LI-2023-03920",
      "source": "linkedin",
      "titre_poste": "Architecte Logiciel Junior",
      "description": "Travail en mode Agile (Scrum/Kanban). Vous serez en charge de développer et maintenir nos applications. Nous recherchons un(e) Architecte Logiciel Junior dynamique pour rejoindre notre équipe. Environnement technique moderne et innovant. Maîtrise de Python; Scala; NLP; Looker; C#; Tableau; Docker requise.",
      "competences_brut": "Python; Scala; NLP; Looker; C#; Tableau; Docker",
      "entreprise": "HPS",
      "ville": "Fès",
      "type_contrat": "Permanent",
      "experience_requise": "min 3 ans",
      "salaire_brut": "45K DH",
      "niveau_etudes": null,
      "secteur": "Informatique / Télécom",
      "date_publication": "2023-05-21",
      "date_expiration": "2023-06-12",
      "nb_postes": 4,
      "teletravail": "Non",
      "langue_requise": [
        "Français"
      ]
    },
    {
      "id_offre": "LI-2023-03933",
      "source": "linkedin",
      "titre_poste": "Cloud Architect",
      "description": "Travail en mode Agile (Scrum/Kanban). Maîtrise de Pandas, NLP requise. Vous serez en charge de développer et maintenir nos applications.",
      "competences_brut": "Pandas • NLP • NumPy",
      "entreprise": "TechMaroc SARL",
      "ville": "CASABLANCA",
      "type_contrat": "CDD",
      "experience_requise": "min 3 ans",
      "salaire_brut": "3234-4888 EUR",
      "niveau_etudes": "Master",
      "secteur": "Santé",
      "date_publication": "2023-05-17",
      "date_expiration": "2023-06-20",
      "nb_postes": 4,
      "teletravail": "Partiel",
      "langue_requise": [
        "Anglais",
        "Arabe"
      ]
    },
    {
      "id_offre": "LI-2023-04014",
      "source": "linkedin",
      "titre_poste": "Architecte Logiciel",
      "description": "Environnement technique moderne et innovant. Travail en mode Agile (Scrum/Kanban). Environnement technique : react.js. Vous serez en charge de développer et maintenir nos applications.",
      "competences_brut": "Docker / Deep Learning",
      "entreprise": "TechMaroc SARL",
      "ville": "casa",
      "type_contrat": "CDD",
      "experience_requise": "Moins de 1 an",
      "salaire_brut": "4726-6709 EUR",
      "niveau_etudes": "Bac+2",
      "secteur": "Énergie",
      "date_publication": "2023-05-17",
      "date_expiration": "2023-06-26",
      "nb_postes": 3,
      "teletravail": "",
      "langue_requise": [
        "Anglais"
      ]
    },
    {
      "id_offre": "LI-2023-04110",
      "source": "linkedin",
      "titre_poste": "Développeur Backend",
      "description": "Mission : participer aux projets stratégiques de l'entreprise. Maîtrise de Git, Jenkins requise. Travail en mode Agile (Scrum/Kanban). Vous serez en charge de développer et maintenir nos applications.",
      "competences_brut": "Jenkins\nGit",
      "entreprise": "Informatique Services",
      "ville": "casa",
      "type_contrat": "CDD",
      "experience_requise": "3 à 5 ans",
      "salaire_brut": "À définir",
      "niveau_etudes": "Bac+2",
      "secteur": "Informatique / Télécom",
      "date_publication": "2023-05-23",
      "date_expiration": "2023-06-18",
      "nb_postes": 4,
      "teletravail": "Partiel",
      "langue_requise": []
    },
    {
      "id_offre": "LI-2023-04119",
      "source": "linkedin",
      "titre_poste": "Ingénieur Big Data Junior",
      "description": "Vous serez en charge de développer et maintenir nos applications. Mission : participer aux projets stratégiques de l'entreprise. Des connaissances en Kafka seraient un plus apprécié.",
      "competences_brut": "Power BI\nHadoop\nMachine Learning\nJenkins",
      "entreprise": "M2M Group",
      "ville": "Fès",
      "type_contrat": "Freelance",
      "experience_requise": "1-2 ans",
      "salaire_brut": "40K DH",
      "niveau_etudes": "Bac+3",
      "secteur": "E-commerce",
      "date_publication": "2023-05-26",
      "date_expiration": "2023-06-21",
      "nb_postes": 2,
      "teletravail": "Oui",
      "langue_requise": []
    },
    {
      "id_offre": "LI-2023-04137",
      "source": "linkedin",
      "titre_poste": "Data Engineer",
      "description": "Nous recherchons un(e) Data Engineer dynamique pour rejoindre notre équipe. Vous serez en charge de développer et maintenir nos applications. Environnement technique : apache spark. Mission : participer aux projets stratégiques de l'entreprise. Environnement technique moderne et innovant.",
      "competences_brut": "Power BI, Django, Azure, Java, Git",
      "entreprise": "Informatique Services",
      "ville": "Fès",
      "type_contrat": "Contrat à durée indéterminée",
      "experience_requise": "min 3 ans",
      "salaire_brut": "18K-25K MAD",
      "niveau_etudes": "Master",
      "secteur": "E-commerce",
      "date_publication": "2023-05-19",
      "date_expiration": "2023-06-22",
      "nb_postes": 3,
      "teletravail": "Oui",
      "langue_requise": [
        "Anglais",
        "Arabe"
      ]
    },
    {
      "id_offre": "LI-2023-04469",
      "source": "linkedin",
      "titre_poste": "Dev Full Stack",
      "description": "Vous serez en charge de développer et maintenir nos applications. Travail en mode Agile (Scrum/Kanban). Environnement technique moderne et innovant. Mission : participer aux projets stratégiques de l'entreprise. Maîtrise de Scikit-learn, Django requise.",
      "competences_brut": "JavaScript • Tableau • Python • Pandas • Scikit-learn • NLP • Django • Machine Learning",
      "entreprise": "Maroc Telecom",
      "ville": "Marrakech",
      "type_contrat": "Permanent",
      "experience_requise": null,
      "salaire_brut": null,
      "niveau_etudes": null,
      "secteur": "Banque / Finance",
      "date_publication": "2023-05-04",
      "date_expiration": "2023-05-28",
      "nb_postes": 5,
      "teletravail": "Hybride",
      "langue_requise": [
        "Anglais"
      ]
    },
    {
      "id_offre": "LI-2023-04490",
      "source": "linkedin",
      "titre_poste": "Développeur Backend",
      "description": "Nous recherchons un(e) Développeur Backend dynamique pour rejoindre notre équipe. Mission : participer aux projets stratégiques de l'entreprise. Maîtrise de Deep Learning, NLP requise. Environnement technique moderne et innovant. Vous serez en charge de développer et maintenir nos applications. Travail en mode Agile (Scrum/Kanban).",
      "competences_brut": "Python\nGit\nJava\nDjango\nNLP\nDeep Learning\nHadoop\nPandas",
      "entreprise": "Attijariwafa",
      "ville": "FEZ",
      "type_contrat": "cdi",
      "experience_requise": "Moins de 1 an",
      "salaire_brut": "4359-7979 EUR",
      "niveau_etudes": "Bac+3",
      "secteur": "Transport",
      "date_publication": "2023-05-05",
      "date_expiration": "2023-06-03",
      "nb_postes": 2,
      "teletravail": "Télétravail complet",
      "langue_requise": [
        "Anglais"
      ]
    },
    {
      "id_offre": "LI-2023-04608",
      "source": "linkedin",
      "titre_poste": "Ingénieur Big Data",
      "description": "Environnement technique moderne et innovant. Vous serez en charge de développer et maintenir nos applications. Nous recherchons un(e) Ingénieur Big Data dynamique pour rejoindre notre équipe. Maîtrise de Pandas, Java requise. Mission : participer aux projets stratégiques de l'entreprise. Travail en mode Agile (Scrum/Kanban).",
      "competences_brut": "Java / Pandas / Looker",
      "entreprise": "Oracle Maroc",
      "ville": "Tanger",
      "type_contrat": "Freelance",
      "experience_requise": "5+ ans",
      "salaire_brut": "19023-23669 MAD",
      "niveau_etudes": "Master",
      "secteur": "E-commerce",
      "date_publication": "2023-05-25",
      "date_expiration": "2023-06-28",
      "nb_postes": 2,
      "teletravail": "Non",
      "langue_requise": [
        "Français",
        "Anglais"
      ]
    },
    {
      "id_offre": "LI-2023-04653",
      "source": "linkedin",
      "titre_poste": "Data Engineer Junior",
      "description": "Environnement technique moderne et innovant. Nous recherchons un(e) Data Engineer Junior dynamique pour rejoindre notre équipe. Vous serez en charge de développer et maintenir nos applications.",
      "competences_brut": "Django • Hadoop • Looker • Tableau",
      "entreprise": "Capgemini",
      "ville": "FEZ",
      "type_contrat": "Stage",
      "experience_requise": "Débutant accepté",
      "salaire_brut": "8334-48897 MAD",
      "niveau_etudes": "Bac+5",
      "secteur": "Banque / Finance",
      "date_publication": "2023-05-04",
      "date_expiration": "2023-06-14",
      "nb_postes": 4,
      "teletravail": "Hybride",
      "langue_requise": [
        "Anglais",
        "Arabe"
      ]
    },
    {
      "id_offre": "LI-2023-04676",
      "source": "linkedin",
      "titre_poste": "Dev Data",
      "description": "Mission : participer aux projets stratégiques de l'entreprise. Nous recherchons un(e) Dev Data dynamique pour rejoindre notre équipe. Environnement technique moderne et innovant. Maîtrise de Angular, Deep Learning requise. Vous serez en charge de développer et maintenir nos applications. Travail en mode Agile (Scrum/Kanban).",
      "competences_brut": "Deep Learning • AWS • Angular",
      "entreprise": "Banque Populaire",
      "ville": "Casablanca",
      "type_contrat": "CDI",
      "experience_requise": "1-2 ans",
      "salaire_brut": "23K DH",
      "niveau_etudes": "Master",
      "secteur": "E-commerce",
      "date_publication": "2023-05-01",
      "date_expiration": "2023-05-28",
      "nb_postes": 2,
      "teletravail": "Télétravail complet",
      "langue_requise": [
        "Anglais",
        "Arabe"
      ]
    },
    {
      "id_offre": "LI-2023-04767",
      "source": "linkedin",
      "titre_poste": "Chef de Projet IT Senior",
      "description": "Nous recherchons un(e) Chef de Projet IT Senior dynamique pour rejoindre notre équipe. Maîtrise de Hadoop, Terraform requise. Environnement technique moderne et innovant.",
      "competences_brut": "Node.js\nNLP\nHadoop\nLooker\nTerraform\nReact\nPython\nR",
      "entreprise": "M2M Group",
      "ville": "Casablanca",
      "type_contrat": "Freelance",
      "experience_requise": "5+ ans",
      "salaire_brut": "Négociable",
      "niveau_etudes": "Bac+3",
      "secteur": "E-commerce",
      "date_publication": "2023-05-26",
      "date_expiration": "2023-07-02",
      "nb_postes": 5,
      "teletravail": "Partiel",
      "langue_requise": []
    },
    {
      "id_offre": "LI-2023-04791",
      "source": "linkedin",
      "titre_poste": "Data Scientist",
      "description": "Nous recherchons un(e) Data Scientist dynamique pour rejoindre notre équipe. Travail en mode Agile (Scrum/Kanban). Mission : participer aux projets stratégiques de l'entreprise. Vous serez en charge de développer et maintenir nos applications. Des connaissances en Java seraient un plus apprécié.",
      "competences_brut": "Kafka • Git • JavaScript • Hadoop • CI/CD",
      "entreprise": "Solutions IT",
      "ville": "MARRAKECH",
      "type_contrat": "Permanent",
      "experience_requise": "3-5 ans",
      "salaire_brut": "3064-3626 EUR",
      "niveau_etudes": "Bac+2",
      "secteur": "Transport",
      "date_publication": "2023-05-08",
      "date_expiration": "2023-05-28",
      "nb_postes": 4,
      "teletravail": "Hybride",
      "langue_requise": [
        "Français"
      ]
    },
    {
      "id_offre": "LI-2023-04833",
      "source": "linkedin",
      "titre_poste": "Analyste Data",
      "description": "Maîtrise de Python; Terraform requise. Mission : participer aux projets stratégiques de l'entreprise. Environnement technique moderne et innovant. Travail en mode Agile (Scrum/Kanban).",
      "competences_brut": "Python; Terraform",
      "entreprise": "Inwi",
      "ville": "Casa",
      "type_contrat": "Stage",
      "experience_requise": "min 3 ans",
      "salaire_brut": null,
      "niveau_etudes": "Bac+5",
      "secteur": "Informatique / Télécom",
      "date_publication": "2023-05-25",
      "date_expiration": "2023-06-24",
      "nb_postes": 5,
      "teletravail": "Partiel",
      "langue_requise": [
        "Français"
      ]
    },
    {
      "id_offre": "LI-2023-04979",
      "source": "linkedin",
      "titre_poste": "Dev Data",
      "description": "Nous recherchons un(e) Dev Data dynamique pour rejoindre notre équipe. Maîtrise de Machine Learning; Airflow; Azure; Java; Hadoop; Django; R; NumPy requise. Environnement technique moderne et innovant. Vous serez en charge de développer et maintenir nos applications. Mission : participer aux projets stratégiques de l'entreprise. Travail en mode Agile (Scrum/Kanban).",
      "competences_brut": "Machine Learning; Airflow; Azure; Java; Hadoop; Django; R; NumPy",
      "entreprise": "Attijariwafa",
      "ville": "Rabat",
      "type_contrat": "Permanent",
      "experience_requise": "Senior (7+ ans)",
      "salaire_brut": "11230-15372 MAD",
      "niveau_etudes": "Bac+3",
      "secteur": "Conseil",
      "date_publication": "2023-05-24",
      "date_expiration": "2023-06-30",
      "nb_postes": 5,
      "teletravail": "Partiel",
      "langue_requise": [
        "Anglais",
        "Arabe"
      ]
    }
  ]
}