{
  "metadata": {
    "source_fichier": "C:\\Users\\dell\\OneDrive\\Bureau\\mexora_rh_lake\\offres_emploi_it_maroc.json",
    "date_ingestion": "2026-04-24T12:20:04.584149",
    "partition": "rekrute/2023_04",
    "nb_offres": 68
  },
  "offres": [
    {
      "id_offre": "RE-2023-00042",
      "source": "rekrute",
      "titre_poste": "Data Analyst",
      "description": "Vous serez en charge de développer et maintenir nos applications. Nous recherchons un(e) Data Analyst dynamique pour rejoindre notre équipe. Mission : participer aux projets stratégiques de l'entreprise.",
      "competences_brut": "Azure\nGit\nC#\nSpring Boot\nTerraform\nScikit-learn",
      "entreprise": "Attijariwafa",
      "ville": "MARRAKECH",
      "type_contrat": "Freelance",
      "experience_requise": "1-2 ans",
      "salaire_brut": "22K-24K MAD",
      "niveau_etudes": "Bac+2",
      "secteur": "Industrie",
      "date_publication": "2023-04-03",
      "date_expiration": "2023-05-01",
      "nb_postes": 5,
      "teletravail": "Partiel",
      "langue_requise": [
        "Anglais"
      ]
    },
    {
      "id_offre": "RE-2023-00156",
      "source": "rekrute",
      "titre_poste": "Data Engineer",
      "description": "Environnement technique moderne et innovant. Maîtrise de Node.js, React requise. Mission : participer aux projets stratégiques de l'entreprise. Environnement technique : django.",
      "competences_brut": "React\nGCP\nLooker\nAWS\nHadoop\nNumPy\nTableau\nNode.js",
      "entreprise": "TechMaroc SARL",
      "ville": "Meknès",
      "type_contrat": "cdi",
      "experience_requise": "Moins de 1 an",
      "salaire_brut": "29K DH",
      "niveau_etudes": null,
      "secteur": "Informatique / Télécom",
      "date_publication": "2023-04-13",
      "date_expiration": "2023-05-23",
      "nb_postes": 3,
      "teletravail": "Partiel",
      "langue_requise": [
        "Anglais",
        "Arabe"
      ]
    },
    {
      "id_offre": "RE-2023-00236",
      "source": "rekrute",
      "titre_poste": "Dev Data Lead",
      "description": "Travail en mode Agile (Scrum/Kanban). Nous recherchons un(e) Dev Data Lead dynamique pour rejoindre notre équipe. Vous serez en charge de développer et maintenir nos applications. Mission : participer aux projets stratégiques de l'entreprise. Maîtrise de C#, Angular requise. Environnement technique moderne et innovant.",
      "competences_brut": "Scala • C# • Airflow • PyTorch • NLP • Looker • Angular • Spark",
      "entreprise": "IBM Maroc",
      "ville": "Fès",
      "type_contrat": "Permanent",
      "experience_requise": "Moins de 1 an",
      "salaire_brut": "16K DH",
      "niveau_etudes": "Bac+2",
      "secteur": "Santé",
      "date_publication": "2023-04-10",
      "date_expiration": "2023-05-16",
      "nb_postes": 5,
      "teletravail": "Non",
      "langue_requise": [
        "Anglais"
      ]
    },
    {
      "id_offre": "RE-2023-00297",
      "source": "rekrute",
      "titre_poste": "Admin Systèmes",
      "description": "Vous serez en charge de développer et maintenir nos applications. Environnement technique moderne et innovant. Travail en mode Agile (Scrum/Kanban). Maîtrise de Tableau, React requise. Nous recherchons un(e) Admin Systèmes dynamique pour rejoindre notre équipe.",
      "competences_brut": "React • PyTorch • Tableau • Spring Boot",
      "entreprise": "KPMG",
      "ville": "CASABLANCA",
      "type_contrat": "Freelance",
      "experience_requise": "Moins de 1 an",
      "salaire_brut": "Confidentiel",
      "niveau_etudes": "Bac+4",
      "secteur": "Transport",
      "date_publication": "2023-04-26",
      "date_expiration": "2023-06-03",
      "nb_postes": 1,
      "teletravail": "",
      "langue_requise": [
        "Français"
      ]
    },
    {
      "id_offre": "RE-2023-00307",
      "source": "rekrute",
      "titre_poste": "Développeur Backend",
      "description": "Mission : participer aux projets stratégiques de l'entreprise. Vous serez en charge de développer et maintenir nos applications. Travail en mode Agile (Scrum/Kanban).",
      "competences_brut": "Django / Power BI / AWS / Java / NLP",
      "entreprise": "IBM Maroc",
      "ville": "Meknès",
      "type_contrat": "Contrat à durée indéterminée",
      "experience_requise": "3 à 5 ans",
      "salaire_brut": "17111-28399 MAD",
      "niveau_etudes": "Bac+4",
      "secteur": "Transport",
      "date_publication": "2023-04-13",
      "date_expiration": "2023-05-08",
      "nb_postes": 5,
      "teletravail": "Non",
      "langue_requise": [
        "Anglais",
        "Arabe"
      ]
    },
    {
      "id_offre": "RE-2023-00468",
      "source": "rekrute",
      "titre_poste": "Architecte Logiciel Senior",
      "description": "Nous recherchons un(e) Architecte Logiciel Senior dynamique pour rejoindre notre équipe. Environnement technique moderne et innovant. Travail en mode Agile (Scrum/Kanban). Mission : participer aux projets stratégiques de l'entreprise.",
      "competences_brut": "Vue.js; Spring Boot; Node.js; Pandas; NumPy; NLP; C#; Django",
      "entreprise": "KPMG",
      "ville": "Casablanca",
      "type_contrat": "Freelance",
      "experience_requise": "5+ ans",
      "salaire_brut": "3627-6646 EUR",
      "niveau_etudes": "Bac+3",
      "secteur": "Énergie",
      "date_publication": "2023-04-04",
      "date_expiration": "2023-05-05",
      "nb_postes": 1,
      "teletravail": "Oui",
      "langue_requise": [
        "Anglais"
      ]
    },
    {
      "id_offre": "RE-2023-00531",
      "source": "rekrute",
      "titre_poste": "Back-end Engineer",
      "description": "Vous serez en charge de développer et maintenir nos applications. Travail en mode Agile (Scrum/Kanban). Nous recherchons un(e) Back-end Engineer dynamique pour rejoindre notre équipe. Maîtrise de Deep Learning, React requise. Environnement technique moderne et innovant.",
      "competences_brut": "React • Deep Learning • Node.js",
      "entreprise": "Deloitte",
      "ville": "MARRAKECH",
      "type_contrat": "CDI",
      "experience_requise": "1-2 ans",
      "salaire_brut": "21599-25975 MAD",
      "niveau_etudes": "Bac+3",
      "secteur": "Industrie",
      "date_publication": "2023-04-19",
      "date_expiration": "2023-04-09",
      "nb_postes": 5,
      "teletravail": "Non",
      "langue_requise": [
        "Anglais",
        "Arabe"
      ]
    },
    {
      "id_offre": "RE-2023-00630",
      "source": "rekrute",
      "titre_poste": "Data Analyst Junior",
      "description": "Mission : participer aux projets stratégiques de l'entreprise. Nous recherchons un(e) Data Analyst Junior dynamique pour rejoindre notre équipe. Des connaissances en Pandas seraient un plus apprécié. Maîtrise de Airflow, Jenkins requise. Travail en mode Agile (Scrum/Kanban). Vous serez en charge de développer et maintenir nos applications.",
      "competences_brut": "NLP / Jenkins / Airflow",
      "entreprise": "Deloitte",
      "ville": "Casa",
      "type_contrat": "CDD",
      "experience_requise": "5+ ans",
      "salaire_brut": null,
      "niveau_etudes": "Master",
      "secteur": "Énergie",
      "date_publication": "2023-04-15",
      "date_expiration": "2023-04-08",
      "nb_postes": 5,
      "teletravail": "Hybride",
      "langue_requise": [
        "Français"
      ]
    },
    {
      "id_offre": "RE-2023-00670",
      "source": "rekrute",
      "titre_poste": "Dev Data",
      "description": "Vous serez en charge de développer et maintenir nos applications. Nous recherchons un(e) Dev Data dynamique pour rejoindre notre équipe. Travail en mode Agile (Scrum/Kanban).",
      "competences_brut": "Jenkins\nAngular\nPyTorch\nSQL",
      "entreprise": "Accenture",
      "ville": "rabat",
      "type_contrat": "cdi",
      "experience_requise": "min 3 ans",
      "salaire_brut": null,
      "niveau_etudes": null,
      "secteur": "Banque / Finance",
      "date_publication": "2023-04-28",
      "date_expiration": "2023-06-03",
      "nb_postes": 5,
      "teletravail": "Partiel",
      "langue_requise": []
    },
    {
      "id_offre": "RE-2023-00680",
      "source": "rekrute",
      "titre_poste": "Fullstack React/Node.js Lead",
      "description": "Vous serez en charge de développer et maintenir nos applications. Mission : participer aux projets stratégiques de l'entreprise. Maîtrise de Python, Vue.js requise. Environnement technique moderne et innovant. Travail en mode Agile (Scrum/Kanban).",
      "competences_brut": "Python, Node.js, CI/CD, Vue.js",
      "entreprise": "CloudMaroc",
      "ville": "Casa",
      "type_contrat": "cdi",
      "experience_requise": null,
      "salaire_brut": "3359-5837 EUR",
      "niveau_etudes": "Licence",
      "secteur": "Santé",
      "date_publication": "2023-04-07",
      "date_expiration": "2023-04-30",
      "nb_postes": 1,
      "teletravail": "Hybride",
      "langue_requise": [
        "Anglais",
        "Arabe"
      ]
    },
    {
      "id_offre": "RE-2023-00864",
      "source": "rekrute",
      "titre_poste": "Architecte Logiciel",
      "description": "Mission : participer aux projets stratégiques de l'entreprise. Travail en mode Agile (Scrum/Kanban). Des connaissances en TensorFlow seraient un plus apprécié. Vous serez en charge de développer et maintenir nos applications. Nous recherchons un(e) Architecte Logiciel dynamique pour rejoindre notre équipe.",
      "competences_brut": "React • Kafka • Machine Learning",
      "entreprise": "Banque Populaire",
      "ville": "MARRAKECH",
      "type_contrat": "CDD",
      "experience_requise": "Débutant accepté",
      "salaire_brut": "4850-5826 EUR",
      "niveau_etudes": "Ingénieur",
      "secteur": "E-commerce",
      "date_publication": "2023-04-04",
      "date_expiration": "2023-05-01",
      "nb_postes": 1,
      "teletravail": "",
      "langue_requise": [
        "Français"
      ]
    },
    {
      "id_offre": "RE-2023-00900",
      "source": "rekrute",
      "titre_poste": "Architecte Logiciel Senior",
      "description": "Nous recherchons un(e) Architecte Logiciel Senior dynamique pour rejoindre notre équipe. Environnement technique : js. Travail en mode Agile (Scrum/Kanban).",
      "competences_brut": "CI/CD • GCP • Hadoop • React • Pandas • R • Scikit-learn",
      "entreprise": "Banque Populaire",
      "ville": "tanger",
      "type_contrat": "Freelance",
      "experience_requise": "Moins de 1 an",
      "salaire_brut": "19115-39715 MAD",
      "niveau_etudes": null,
      "secteur": "Banque / Finance",
      "date_publication": "2023-04-11",
      "date_expiration": "2023-05-22",
      "nb_postes": 5,
      "teletravail": "Non",
      "langue_requise": [
        "Anglais",
        "Arabe"
      ]
    },
    {
      "id_offre": "RE-2023-00929",
      "source": "rekrute",
      "titre_poste": "Analyste Data",
      "description": "Nous recherchons un(e) Analyste Data dynamique pour rejoindre notre équipe. Vous serez en charge de développer et maintenir nos applications. Environnement technique moderne et innovant. Environnement technique : synapse. Travail en mode Agile (Scrum/Kanban). Maîtrise de Kubernetes, Azure requise.",
      "competences_brut": "Airflow, Kubernetes, Power BI, Jenkins, Spark, Azure, Deep Learning",
      "entreprise": "Attijariwafa",
      "ville": "tanger",
      "type_contrat": "Permanent",
      "experience_requise": "3 à 5 ans",
      "salaire_brut": "3195-6731 EUR",
      "niveau_etudes": "Master",
      "secteur": "Transport",
      "date_publication": "2023-04-07",
      "date_expiration": "2023-05-11",
      "nb_postes": 2,
      "teletravail": "",
      "langue_requise": [
        "Français",
        "Anglais"
      ]
    },
    {
      "id_offre": "RE-2023-00933",
      "source": "rekrute",
      "titre_poste": "Scientifique des données Senior",
      "description": "Mission : participer aux projets stratégiques de l'entreprise. Maîtrise de Airflow; Looker; Spring Boot requise. Nous recherchons un(e) Scientifique des données Senior dynamique pour rejoindre notre équipe. Travail en mode Agile (Scrum/Kanban).",
      "competences_brut": "Airflow; Looker; Spring Boot",
      "entreprise": "Capgemini",
      "ville": "rabat",
      "type_contrat": "cdi",
      "experience_requise": "5+ ans",
      "salaire_brut": "11K-32K MAD",
      "niveau_etudes": null,
      "secteur": "Conseil",
      "date_publication": "2023-04-02",
      "date_expiration": "2023-05-16",
      "nb_postes": 3,
      "teletravail": "Partiel",
      "langue_requise": [
        "Anglais",
        "Arabe"
      ]
    },
    {
      "id_offre": "RE-2023-00958",
      "source": "rekrute",
      "titre_poste": "Data Engineer Junior Lead",
      "description": "Nous recherchons un(e) Data Engineer Junior Lead dynamique pour rejoindre notre équipe. Vous serez en charge de développer et maintenir nos applications. Environnement technique : r-studio. Travail en mode Agile (Scrum/Kanban).",
      "competences_brut": "React; Terraform; PyTorch; JavaScript; Jenkins; Hadoop; Node.js; Angular",
      "entreprise": "Oracle Maroc",
      "ville": "rabat",
      "type_contrat": "cdi",
      "experience_requise": "min 3 ans",
      "salaire_brut": "16K DH",
      "niveau_etudes": "Bac+2",
      "secteur": "Santé",
      "date_publication": "2023-04-27",
      "date_expiration": "2023-06-04",
      "nb_postes": 4,
      "teletravail": "Non",
      "langue_requise": [
        "Français"
      ]
    },
    {
      "id_offre": "RE-2023-01029",
      "source": "rekrute",
      "titre_poste": "Dev Data Lead",
      "description": "Nous recherchons un(e) Dev Data Lead dynamique pour rejoindre notre équipe. Environnement technique moderne et innovant. Travail en mode Agile (Scrum/Kanban). Mission : participer aux projets stratégiques de l'entreprise. Vous serez en charge de développer et maintenir nos applications. Des connaissances en Python seraient un plus apprécié.",
      "competences_brut": "NumPy\nDeep Learning\nJava\nSpark\nPower BI\nAngular",
      "entreprise": "Solutions IT",
      "ville": "Tanger",
      "type_contrat": "Contrat à durée indéterminée",
      "experience_requise": null,
      "salaire_brut": "2331-5060 EUR",
      "niveau_etudes": null,
      "secteur": "Santé",
      "date_publication": "2023-04-13",
      "date_expiration": "2023-05-28",
      "nb_postes": 1,
      "teletravail": "",
      "langue_requise": [
        "Anglais",
        "Arabe"
      ]
    },
    {
      "id_offre": "RE-2023-01031",
      "source": "rekrute",
      "titre_poste": "Data Analyst Junior Lead",
      "description": "Nous recherchons un(e) Data Analyst Junior Lead dynamique pour rejoindre notre équipe. Travail en mode Agile (Scrum/Kanban). Mission : participer aux projets stratégiques de l'entreprise. Vous serez en charge de développer et maintenir nos applications. Environnement technique moderne et innovant.",
      "competences_brut": "Spark; C#",
      "entreprise": "Wafasalaf",
      "ville": "Casablanca",
      "type_contrat": "CDI",
      "experience_requise": "",
      "salaire_brut": "8733-15597 MAD",
      "niveau_etudes": "Ingénieur",
      "secteur": "Transport",
      "date_publication": "2023-04-27",
      "date_expiration": "2023-05-20",
      "nb_postes": 2,
      "teletravail": "Partiel",
      "langue_requise": [
        "Anglais"
      ]
    },
    {
      "id_offre": "RE-2023-01041",
      "source": "rekrute",
      "titre_poste": "Dev Full Stack",
      "description": "Nous recherchons un(e) Dev Full Stack dynamique pour rejoindre notre équipe. Travail en mode Agile (Scrum/Kanban). Maîtrise de Scala; Kubernetes; Spring Boot; Angular requise. Mission : participer aux projets stratégiques de l'entreprise. Des connaissances en Airflow seraient un plus apprécié. Vous serez en charge de développer et maintenir nos applications.",
      "competences_brut": "Scala; Kubernetes; Spring Boot; Angular",
      "entreprise": "KPMG",
      "ville": "Meknès",
      "type_contrat": "Contrat à durée indéterminée",
      "experience_requise": "Senior (7+ ans)",
      "salaire_brut": "30K DH",
      "niveau_etudes": "Bac+5",
      "secteur": "Santé",
      "date_publication": "2023-04-07",
      "date_expiration": "2023-04-28",
      "nb_postes": 1,
      "teletravail": "Partiel",
      "langue_requise": [
        "Français"
      ]
    },
    {
      "id_offre": "RE-2023-01212",
      "source": "rekrute",
      "titre_poste": "Back-end Engineer",
      "description": "Travail en mode Agile (Scrum/Kanban). Des connaissances en Vue.js seraient un plus apprécié. Vous serez en charge de développer et maintenir nos applications. Maîtrise de Jenkins; R; TensorFlow; C#; Looker requise. Mission : participer aux projets stratégiques de l'entreprise. Nous recherchons un(e) Back-end Engineer dynamique pour rejoindre notre équipe.",
      "competences_brut": "Jenkins; R; TensorFlow; C#; Looker",
      "entreprise": "DataSmart",
      "ville": "Rabat",
      "type_contrat": "CDI",
      "experience_requise": "Senior (7+ ans)",
      "salaire_brut": "4569-7521 EUR",
      "niveau_etudes": "Bac+4",
      "secteur": "Industrie",
      "date_publication": "2023-04-20",
      "date_expiration": "2023-05-11",
      "nb_postes": 2,
      "teletravail": "Partiel",
      "langue_requise": [
        "Anglais"
      ]
    },
    {
      "id_offre": "RE-2023-01251",
      "source": "rekrute",
      "titre_poste": "Machine Learning Engineer",
      "description": "Environnement technique moderne et innovant. Nous recherchons un(e) Machine Learning Engineer dynamique pour rejoindre notre équipe. Mission : participer aux projets stratégiques de l'entreprise. Maîtrise de Docker; PyTorch; Scikit-learn; Python; Kubernetes; Angular; Kafka requise.",
      "competences_brut": "Docker; PyTorch; Scikit-learn; Python; Kubernetes; Angular; Kafka",
      "entreprise": "M2M Group",
      "ville": "Tanger",
      "type_contrat": "Stage",
      "experience_requise": "3 à 5 ans",
      "salaire_brut": "42K DH",
      "niveau_etudes": "Master",
      "secteur": "E-commerce",
      "date_publication": "2023-04-27",
      "date_expiration": "2023-05-25",
      "nb_postes": 1,
      "teletravail": "Non",
      "langue_requise": [
        "Anglais",
        "Arabe"
      ]
    },
    {
      "id_offre": "RE-2023-01299",
      "source": "rekrute",
      "titre_poste": "Machine Learning Engineer",
      "description": "Mission : participer aux projets stratégiques de l'entreprise. Travail en mode Agile (Scrum/Kanban). Environnement technique moderne et innovant. Des connaissances en GCP seraient un plus apprécié. Maîtrise de Power BI, PyTorch requise. Nous recherchons un(e) Machine Learning Engineer dynamique pour rejoindre notre équipe.",
      "competences_brut": "Power BI / Kubernetes / PyTorch / Docker",
      "entreprise": "CloudMaroc",
      "ville": "CASABLANCA",
      "type_contrat": "Stage",
      "experience_requise": "Senior (7+ ans)",
      "salaire_brut": "19K-31K MAD",
      "niveau_etudes": "Ingénieur",
      "secteur": "Informatique / Télécom",
      "date_publication": "2023-04-08",
      "date_expiration": "2023-05-07",
      "nb_postes": 3,
      "teletravail": "Télétravail complet",
      "langue_requise": [
        "Français"
      ]
    },
    {
      "id_offre": "RE-2023-01439",
      "source": "rekrute",
      "titre_poste": "Data Scientist",
      "description": "Nous recherchons un(e) Data Scientist dynamique pour rejoindre notre équipe. Travail en mode Agile (Scrum/Kanban). Vous serez en charge de développer et maintenir nos applications.",
      "competences_brut": "C#, Kafka, Machine Learning, Terraform",
      "entreprise": "TechMaroc SARL",
      "ville": "TANGER",
      "type_contrat": "CDI",
      "experience_requise": "3 à 5 ans",
      "salaire_brut": "20077-29342 MAD",
      "niveau_etudes": "Bac+5",
      "secteur": "Santé",
      "date_publication": "2023-04-22",
      "date_expiration": "2023-05-19",
      "nb_postes": 2,
      "teletravail": "Partiel",
      "langue_requise": [
        "Anglais"
      ]
    },
    {
      "id_offre": "RE-2023-01575",
      "source": "rekrute",
      "titre_poste": "Dev Data",
      "description": "Nous recherchons un(e) Dev Data dynamique pour rejoindre notre équipe. Environnement technique moderne et innovant. Maîtrise de Python, Scala requise.",
      "competences_brut": "PyTorch • Airflow • Terraform • Scala • Python • Pandas • Power BI • Git",
      "entreprise": "Informatique Services",
      "ville": "Rabat",
      "type_contrat": "cdi",
      "experience_requise": "5+ ans",
      "salaire_brut": "22K-26K MAD",
      "niveau_etudes": "Bac+4",
      "secteur": "Informatique / Télécom",
      "date_publication": "2023-04-18",
      "date_expiration": "2023-05-25",
      "nb_postes": 5,
      "teletravail": "Télétravail complet",
      "langue_requise": [
        "Français"
      ]
    },
    {
      "id_offre": "RE-2023-01851",
      "source": "rekrute",
      "titre_poste": "Data Eng.",
      "description": "Environnement technique moderne et innovant. Vous serez en charge de développer et maintenir nos applications. Mission : participer aux projets stratégiques de l'entreprise. Travail en mode Agile (Scrum/Kanban). Nous recherchons un(e) Data Eng. dynamique pour rejoindre notre équipe.",
      "competences_brut": "PyTorch • Scikit-learn • R • Docker • Spark",
      "entreprise": "IBM Maroc",
      "ville": "Casablanca",
      "type_contrat": "cdi",
      "experience_requise": "3 à 5 ans",
      "salaire_brut": "2893-4970 EUR",
      "niveau_etudes": "Bac+3",
      "secteur": "Conseil",
      "date_publication": "2023-04-26",
      "date_expiration": "2023-05-27",
      "nb_postes": 3,
      "teletravail": "Hybride",
      "langue_requise": [
        "Anglais"
      ]
    },
    {
      "id_offre": "RE-2023-01911",
      "source": "rekrute",
      "titre_poste": "Cloud Architect Lead",
      "description": "Mission : participer aux projets stratégiques de l'entreprise. Travail en mode Agile (Scrum/Kanban). Nous recherchons un(e) Cloud Architect Lead dynamique pour rejoindre notre équipe. Environnement technique moderne et innovant. Vous serez en charge de développer et maintenir nos applications.",
      "competences_brut": "Azure / React",
      "entreprise": "CloudMaroc",
      "ville": "Meknès",
      "type_contrat": "Contrat à durée indéterminée",
      "experience_requise": "Moins de 1 an",
      "salaire_brut": "18K-26K MAD",
      "niveau_etudes": "Bac+3",
      "secteur": "Informatique / Télécom",
      "date_publication": "2023-04-23",
      "date_expiration": "2023-05-14",
      "nb_postes": 4,
      "teletravail": "",
      "langue_requise": [
        "Français",
        "Anglais"
      ]
    },
    {
      "id_offre": "RE-2023-01925",
      "source": "rekrute",
      "titre_poste": "Back-end Engineer",
      "description": "Vous serez en charge de développer et maintenir nos applications. Environnement technique moderne et innovant. Travail en mode Agile (Scrum/Kanban).",
      "competences_brut": "Airflow\nGit",
      "entreprise": "HPS",
      "ville": "Rabat",
      "type_contrat": "Permanent",
      "experience_requise": "1-2 ans",
      "salaire_brut": "15K-35K MAD",
      "niveau_etudes": null,
      "secteur": "Transport",
      "date_publication": "2023-04-20",
      "date_expiration": "2023-05-30",
      "nb_postes": 2,
      "teletravail": "Hybride",
      "langue_requise": [
        "Anglais",
        "Arabe"
      ]
    },
    {
      "id_offre": "RE-2023-01940",
      "source": "rekrute",
      "titre_poste": "Architecte Logiciel",
      "description": "Nous recherchons un(e) Architecte Logiciel dynamique pour rejoindre notre équipe. Environnement technique moderne et innovant. Travail en mode Agile (Scrum/Kanban). Maîtrise de NLP, Machine Learning requise.",
      "competences_brut": "Machine Learning / NLP / Hadoop / Scala",
      "entreprise": "Deloitte",
      "ville": "Casablanca",
      "type_contrat": "CDD",
      "experience_requise": "1-2 ans",
      "salaire_brut": null,
      "niveau_etudes": "Bac+4",
      "secteur": "Conseil",
      "date_publication": "2023-04-09",
      "date_expiration": "2023-05-20",
      "nb_postes": 3,
      "teletravail": "Télétravail complet",
      "langue_requise": [
        "Français",
        "Anglais"
      ]
    },
    {
      "id_offre": "RE-2023-02021",
      "source": "rekrute",
      "titre_poste": "Data Analyst",
      "description": "Mission : participer aux projets stratégiques de l'entreprise. Des connaissances en Docker seraient un plus apprécié. Nous recherchons un(e) Data Analyst dynamique pour rejoindre notre équipe. Travail en mode Agile (Scrum/Kanban).",
      "competences_brut": "Looker / Django / SQL / Hadoop / Scala",
      "entreprise": "Informatique Services",
      "ville": "Casa",
      "type_contrat": "Freelance",
      "experience_requise": "Débutant accepté",
      "salaire_brut": "10K DH",
      "niveau_etudes": null,
      "secteur": "Transport",
      "date_publication": "2023-04-03",
      "date_expiration": "2023-05-02",
      "nb_postes": 3,
      "teletravail": "Partiel",
      "langue_requise": []
    },
    {
      "id_offre": "RE-2023-02071",
      "source": "rekrute",
      "titre_poste": "Admin Systèmes Senior",
      "description": "Environnement technique moderne et innovant. Maîtrise de Java, React requise. Mission : participer aux projets stratégiques de l'entreprise.",
      "competences_brut": "React\nJava\nDocker",
      "entreprise": "Oracle Maroc",
      "ville": "RABAT",
      "type_contrat": "cdi",
      "experience_requise": "3-5 ans",
      "salaire_brut": "42K DH",
      "niveau_etudes": "Bac+2",
      "secteur": "Banque / Finance",
      "date_publication": "2023-04-12",
      "date_expiration": "2023-05-15",
      "nb_postes": 4,
      "teletravail": "Hybride",
      "langue_requise": []
    },
    {
      "id_offre": "RE-2023-02090",
      "source": "rekrute",
      "titre_poste": "Data Engineer Lead",
      "description": "Vous serez en charge de développer et maintenir nos applications. Environnement technique moderne et innovant. Nous recherchons un(e) Data Engineer Lead dynamique pour rejoindre notre équipe. Maîtrise de Hadoop, R requise. Mission : participer aux projets stratégiques de l'entreprise. Travail en mode Agile (Scrum/Kanban).",
      "competences_brut": "NLP • Node.js • R • Hadoop • CI/CD",
      "entreprise": "Informatique Services",
      "ville": "casa",
      "type_contrat": "CDD",
      "experience_requise": "min 3 ans",
      "salaire_brut": "3982-6225 EUR",
      "niveau_etudes": "Licence",
      "secteur": "Informatique / Télécom",
      "date_publication": "2023-04-03",
      "date_expiration": "2023-05-06",
      "nb_postes": 3,
      "teletravail": "Oui",
      "langue_requise": [
        "Français"
      ]
    },
    {
      "id_offre": "RE-2023-02193",
      "source": "rekrute",
      "titre_poste": "Chef de Projet IT",
      "description": "Environnement technique moderne et innovant. Environnement technique : spring boot. Travail en mode Agile (Scrum/Kanban). Vous serez en charge de développer et maintenir nos applications. Maîtrise de Jenkins, SQL requise. Mission : participer aux projets stratégiques de l'entreprise.",
      "competences_brut": "Jenkins\nAzure\nGCP\nSpring Boot\nReact\nPython\nKubernetes\nSQL",
      "entreprise": "Orange Maroc",
      "ville": "Casablanca",
      "type_contrat": "Permanent",
      "experience_requise": "Senior (7+ ans)",
      "salaire_brut": "Négociable",
      "niveau_etudes": "Bac+4",
      "secteur": "Banque / Finance",
      "date_publication": "2023-04-17",
      "date_expiration": "2023-05-11",
      "nb_postes": 4,
      "teletravail": "Télétravail complet",
      "langue_requise": []
    },
    {
      "id_offre": "RE-2023-02258",
      "source": "rekrute",
      "titre_poste": "Data Analyst",
      "description": "Nous recherchons un(e) Data Analyst dynamique pour rejoindre notre équipe. Travail en mode Agile (Scrum/Kanban). Mission : participer aux projets stratégiques de l'entreprise. Vous serez en charge de développer et maintenir nos applications.",
      "competences_brut": "Scala; Spark; NLP; PyTorch; Deep Learning; Django",
      "entreprise": "KPMG",
      "ville": "MARRAKECH",
      "type_contrat": "Stage",
      "experience_requise": "3-5 ans",
      "salaire_brut": null,
      "niveau_etudes": "Bac+3",
      "secteur": "Énergie",
      "date_publication": "2023-04-21",
      "date_expiration": "2023-05-28",
      "nb_postes": 2,
      "teletravail": "Non",
      "langue_requise": [
        "Français",
        "Anglais"
      ]
    },
    {
      "id_offre": "RE-2023-02308",
      "source": "rekrute",
      "titre_poste": "Machine Learning Engineer",
      "description": "Vous serez en charge de développer et maintenir nos applications. Environnement technique moderne et innovant. Maîtrise de AWS, Azure requise. Mission : participer aux projets stratégiques de l'entreprise. Travail en mode Agile (Scrum/Kanban). Nous recherchons un(e) Machine Learning Engineer dynamique pour rejoindre notre équipe.",
      "competences_brut": "Azure / AWS",
      "entreprise": "DataSmart",
      "ville": "Tanger",
      "type_contrat": "Freelance",
      "experience_requise": "5+ ans",
      "salaire_brut": "22001-40067 MAD",
      "niveau_etudes": "Bac+3",
      "secteur": "Santé",
      "date_publication": "2023-04-09",
      "date_expiration": "2023-05-21",
      "nb_postes": 3,
      "teletravail": "",
      "langue_requise": [
        "Français",
        "Anglais"
      ]
    },
    {
      "id_offre": "RE-2023-02532",
      "source": "rekrute",
      "titre_poste": "Data Engineer Junior Lead",
      "description": "Travail en mode Agile (Scrum/Kanban). Nous recherchons un(e) Data Engineer Junior Lead dynamique pour rejoindre notre équipe. Des connaissances en GCP seraient un plus apprécié.",
      "competences_brut": "Terraform / AWS / Airflow / Scala / Django / JavaScript / Scikit-learn / Tableau",
      "entreprise": "Attijariwafa",
      "ville": "Casa",
      "type_contrat": "CDD",
      "experience_requise": null,
      "salaire_brut": "Selon profil",
      "niveau_etudes": "Licence",
      "secteur": "Transport",
      "date_publication": "2023-04-02",
      "date_expiration": "2023-04-25",
      "nb_postes": 5,
      "teletravail": "",
      "langue_requise": [
        "Français",
        "Anglais"
      ]
    },
    {
      "id_offre": "RE-2023-02672",
      "source": "rekrute",
      "titre_poste": "Back-end Engineer",
      "description": "Mission : participer aux projets stratégiques de l'entreprise. Vous serez en charge de développer et maintenir nos applications. Environnement technique moderne et innovant. Travail en mode Agile (Scrum/Kanban). Maîtrise de Terraform, Django requise.",
      "competences_brut": "Deep Learning\nTerraform\nAzure\nDjango",
      "entreprise": "Maroc Telecom",
      "ville": "Tanger",
      "type_contrat": "CDD",
      "experience_requise": "",
      "salaire_brut": "16K DH",
      "niveau_etudes": "Bac+2",
      "secteur": "Informatique / Télécom",
      "date_publication": "2023-04-27",
      "date_expiration": "2023-05-27",
      "nb_postes": 4,
      "teletravail": "Oui",
      "langue_requise": [
        "Français"
      ]
    },
    {
      "id_offre": "RE-2023-02857",
      "source": "rekrute",
      "titre_poste": "Data Analyst",
      "description": "Environnement technique moderne et innovant. Vous serez en charge de développer et maintenir nos applications. Travail en mode Agile (Scrum/Kanban). Environnement technique : python. Nous recherchons un(e) Data Analyst dynamique pour rejoindre notre équipe. Mission : participer aux projets stratégiques de l'entreprise.",
      "competences_brut": "TensorFlow • Git • Looker • Kafka • JavaScript • Django • Kubernetes",
      "entreprise": "Inwi",
      "ville": "FEZ",
      "type_contrat": "Freelance",
      "experience_requise": "",
      "salaire_brut": "À définir",
      "niveau_etudes": "Bac+4",
      "secteur": "E-commerce",
      "date_publication": "2023-04-08",
      "date_expiration": "2023-05-13",
      "nb_postes": 4,
      "teletravail": "Non",
      "langue_requise": [
        "Anglais",
        "Arabe"
      ]
    },
    {
      "id_offre": "RE-2023-02936",
      "source": "rekrute",
      "titre_poste": "Architecte Logiciel",
      "description": "Mission : participer aux projets stratégiques de l'entreprise. Travail en mode Agile (Scrum/Kanban). Environnement technique moderne et innovant. Nous recherchons un(e) Architecte Logiciel dynamique pour rejoindre notre équipe. Vous serez en charge de développer et maintenir nos applications.",
      "competences_brut": "Pandas\nAzure\nPower BI\nJava\nSpark",
      "entreprise": "Oracle Maroc",
      "ville": "Rabat",
      "type_contrat": "CDI",
      "experience_requise": "min 3 ans",
      "salaire_brut": "3318-4798 EUR",
      "niveau_etudes": null,
      "secteur": "Énergie",
      "date_publication": "2023-04-26",
      "date_expiration": "2023-06-09",
      "nb_postes": 2,
      "teletravail": "Télétravail complet",
      "langue_requise": [
        "Français"
      ]
    },
    {
      "id_offre": "RE-2023-02951",
      "source": "rekrute",
      "titre_poste": "Data Analyst",
      "description": "Maîtrise de CD, AWS requise. Nous recherchons un(e) Data Analyst dynamique pour rejoindre notre équipe. Travail en mode Agile (Scrum/Kanban). Vous serez en charge de développer et maintenir nos applications. Des connaissances en Vue.js seraient un plus apprécié. Environnement technique moderne et innovant.",
      "competences_brut": "CI/CD, AWS, GCP",
      "entreprise": "Attijariwafa",
      "ville": "Marrakech",
      "type_contrat": "CDD",
      "experience_requise": "",
      "salaire_brut": "21K DH",
      "niveau_etudes": "Bac+2",
      "secteur": "Informatique / Télécom",
      "date_publication": "2023-04-18",
      "date_expiration": "2023-05-24",
      "nb_postes": 3,
      "teletravail": "Hybride",
      "langue_requise": [
        "Anglais"
      ]
    },
    {
      "id_offre": "RE-2023-02955",
      "source": "rekrute",
      "titre_poste": "Machine Learning Engineer",
      "description": "Vous serez en charge de développer et maintenir nos applications. Travail en mode Agile (Scrum/Kanban). Maîtrise de R, Node.js requise. Environnement technique moderne et innovant. Mission : participer aux projets stratégiques de l'entreprise. Nous recherchons un(e) Machine Learning Engineer dynamique pour rejoindre notre équipe.",
      "competences_brut": "Node.js / R",
      "entreprise": "HPS",
      "ville": "Rabat",
      "type_contrat": "cdi",
      "experience_requise": "5+ ans",
      "salaire_brut": "Selon profil",
      "niveau_etudes": "Bac+5",
      "secteur": "Énergie",
      "date_publication": "2023-04-07",
      "date_expiration": "2023-05-08",
      "nb_postes": 1,
      "teletravail": "Télétravail complet",
      "langue_requise": [
        "Français"
      ]
    },
    {
      "id_offre": "RE-2023-03001",
      "source": "rekrute",
      "titre_poste": "Data Engineer",
      "description": "Maîtrise de Vue.js, Git requise. Nous recherchons un(e) Data Engineer dynamique pour rejoindre notre équipe. Environnement technique moderne et innovant.",
      "competences_brut": "Scikit-learn / Tableau / Git / Jenkins / Vue.js / Kubernetes",
      "entreprise": "M2M Group",
      "ville": "rabat",
      "type_contrat": "Contrat à durée indéterminée",
      "experience_requise": "3 à 5 ans",
      "salaire_brut": "11698-47539 MAD",
      "niveau_etudes": "Bac+4",
      "secteur": "Informatique / Télécom",
      "date_publication": "2023-04-25",
      "date_expiration": "2023-05-21",
      "nb_postes": 5,
      "teletravail": "Oui",
      "langue_requise": [
        "Anglais",
        "Arabe"
      ]
    },
    {
      "id_offre": "RE-2023-03077",
      "source": "rekrute",
      "titre_poste": "Analyste Data",
      "description": "Des connaissances en CI/CD seraient un plus apprécié. Maîtrise de Django, Spring Boot requise. Vous serez en charge de développer et maintenir nos applications. Nous recherchons un(e) Analyste Data dynamique pour rejoindre notre équipe.",
      "competences_brut": "Django\nPython\nSpring Boot\nCI/CD",
      "entreprise": "Orange Maroc",
      "ville": "Marrakech",
      "type_contrat": "CDI",
      "experience_requise": "",
      "salaire_brut": "Selon profil",
      "niveau_etudes": "Master",
      "secteur": "Énergie",
      "date_publication": "2023-04-29",
      "date_expiration": "2023-05-30",
      "nb_postes": 2,
      "teletravail": "Non",
      "langue_requise": []
    },
    {
      "id_offre": "RE-2023-03123",
      "source": "rekrute",
      "titre_poste": "Scientifique des données",
      "description": "Travail en mode Agile (Scrum/Kanban). Des connaissances en Deep Learning seraient un plus apprécié. Nous recherchons un(e) Scientifique des données dynamique pour rejoindre notre équipe. Environnement technique moderne et innovant. Vous serez en charge de développer et maintenir nos applications. Maîtrise de PyTorch; Tableau; Jenkins; Machine Learning; Terraform; Deep Learning; Vue.js requise.",
      "competences_brut": "PyTorch; Tableau; Jenkins; Machine Learning; Terraform; Deep Learning; Vue.js",
      "entreprise": "M2M Group",
      "ville": "Meknès",
      "type_contrat": "CDD",
      "experience_requise": "5+ ans",
      "salaire_brut": null,
      "niveau_etudes": "Bac+5",
      "secteur": "Industrie",
      "date_publication": "2023-04-25",
      "date_expiration": "2023-05-24",
      "nb_postes": 3,
      "teletravail": "",
      "langue_requise": [
        "Anglais",
        "Arabe"
      ]
    },
    {
      "id_offre": "RE-2023-03296",
      "source": "rekrute",
      "titre_poste": "Fullstack React/Node.js",
      "description": "Vous serez en charge de développer et maintenir nos applications. Maîtrise de JavaScript, Scikit-learn requise. Mission : participer aux projets stratégiques de l'entreprise. Des connaissances en Machine Learning seraient un plus apprécié.",
      "competences_brut": "Java / GCP / Scikit-learn / JavaScript",
      "entreprise": "Banque Populaire",
      "ville": "MARRAKECH",
      "type_contrat": "cdi",
      "experience_requise": "",
      "salaire_brut": null,
      "niveau_etudes": "Bac+4",
      "secteur": "Transport",
      "date_publication": "2023-04-11",
      "date_expiration": "2023-05-23",
      "nb_postes": 1,
      "teletravail": "",
      "langue_requise": [
        "Français",
        "Anglais"
      ]
    },
    {
      "id_offre": "RE-2023-03405",
      "source": "rekrute",
      "titre_poste": "Data Analyst",
      "description": "Nous recherchons un(e) Data Analyst dynamique pour rejoindre notre équipe. Environnement technique moderne et innovant. Mission : participer aux projets stratégiques de l'entreprise. Vous serez en charge de développer et maintenir nos applications.",
      "competences_brut": "C#, GCP, NumPy, Django, Deep Learning, JavaScript",
      "entreprise": "Accenture",
      "ville": "Marrakech",
      "type_contrat": "Contrat à durée indéterminée",
      "experience_requise": "Débutant accepté",
      "salaire_brut": "2128-6460 EUR",
      "niveau_etudes": "Licence",
      "secteur": "Informatique / Télécom",
      "date_publication": "2023-04-27",
      "date_expiration": "2023-06-11",
      "nb_postes": 5,
      "teletravail": "",
      "langue_requise": [
        "Anglais"
      ]
    },
    {
      "id_offre": "RE-2023-03416",
      "source": "rekrute",
      "titre_poste": "Ingénieur Big Data",
      "description": "Nous recherchons un(e) Ingénieur Big Data dynamique pour rejoindre notre équipe. Des connaissances en Tableau seraient un plus apprécié. Vous serez en charge de développer et maintenir nos applications.",
      "competences_brut": "Java, Hadoop, AWS, SQL, NumPy",
      "entreprise": "PwC",
      "ville": "Meknès",
      "type_contrat": "CDD",
      "experience_requise": "5+ ans",
      "salaire_brut": "Confidentiel",
      "niveau_etudes": null,
      "secteur": "Transport",
      "date_publication": "2023-04-27",
      "date_expiration": "2023-05-29",
      "nb_postes": 5,
      "teletravail": "Oui",
      "langue_requise": [
        "Anglais",
        "Arabe"
      ]
    },
    {
      "id_offre": "RE-2023-03485",
      "source": "rekrute",
      "titre_poste": "Data Eng.",
      "description": "Environnement technique moderne et innovant. Nous recherchons un(e) Data Eng. dynamique pour rejoindre notre équipe. Mission : participer aux projets stratégiques de l'entreprise. Des connaissances en Spring Boot seraient un plus apprécié.",
      "competences_brut": "Django\nKubernetes\nTensorFlow\nJenkins",
      "entreprise": "TechMaroc SARL",
      "ville": "FEZ",
      "type_contrat": "Permanent",
      "experience_requise": "3 à 5 ans",
      "salaire_brut": "18621-24698 MAD",
      "niveau_etudes": null,
      "secteur": "Énergie",
      "date_publication": "2023-04-15",
      "date_expiration": "2023-05-18",
      "nb_postes": 2,
      "teletravail": "Partiel",
      "langue_requise": []
    },
    {
      "id_offre": "RE-2023-03542",
      "source": "rekrute",
      "titre_poste": "Data Scientist",
      "description": "Mission : participer aux projets stratégiques de l'entreprise. Vous serez en charge de développer et maintenir nos applications. Travail en mode Agile (Scrum/Kanban). Environnement technique moderne et innovant. Nous recherchons un(e) Data Scientist dynamique pour rejoindre notre équipe.",
      "competences_brut": "AWS / Django / Jenkins / Power BI / GCP / Hadoop / React / Scala",
      "entreprise": "Deloitte",
      "ville": "rabat",
      "type_contrat": "CDD",
      "experience_requise": "3 à 5 ans",
      "salaire_brut": "2516-6762 EUR",
      "niveau_etudes": "Master",
      "secteur": "Industrie",
      "date_publication": "2023-04-15",
      "date_expiration": "2023-05-08",
      "nb_postes": 3,
      "teletravail": "",
      "langue_requise": [
        "Français"
      ]
    },
    {
      "id_offre": "RE-2023-03639",
      "source": "rekrute",
      "titre_poste": "Data Engineer",
      "description": "Vous serez en charge de développer et maintenir nos applications. Nous recherchons un(e) Data Engineer dynamique pour rejoindre notre équipe. Des connaissances en Looker seraient un plus apprécié. Environnement technique moderne et innovant.",
      "competences_brut": "Azure; Machine Learning; Scikit-learn; Terraform; C#; Docker; Git; GCP",
      "entreprise": "DataSmart",
      "ville": "casa",
      "type_contrat": "Permanent",
      "experience_requise": "Moins de 1 an",
      "salaire_brut": "19266-45918 MAD",
      "niveau_etudes": null,
      "secteur": "Transport",
      "date_publication": "2023-04-02",
      "date_expiration": "2023-05-08",
      "nb_postes": 5,
      "teletravail": "Partiel",
      "langue_requise": [
        "Français"
      ]
    },
    {
      "id_offre": "RE-2023-03749",
      "source": "rekrute",
      "titre_poste": "Dev Data Lead",
      "description": "Nous recherchons un(e) Dev Data Lead dynamique pour rejoindre notre équipe. Travail en mode Agile (Scrum/Kanban). Environnement technique moderne et innovant.",
      "competences_brut": "Terraform, Spark, R",
      "entreprise": "Solutions IT",
      "ville": "tanger",
      "type_contrat": "Freelance",
      "experience_requise": "3-5 ans",
      "salaire_brut": null,
      "niveau_etudes": "Bac+3",
      "secteur": "Industrie",
      "date_publication": "2023-04-12",
      "date_expiration": "2023-05-15",
      "nb_postes": 2,
      "teletravail": "",
      "langue_requise": [
        "Anglais"
      ]
    },
    {
      "id_offre": "RE-2023-03773",
      "source": "rekrute",
      "titre_poste": "Développeur Full Stack",
      "description": "Mission : participer aux projets stratégiques de l'entreprise. Nous recherchons un(e) Développeur Full Stack dynamique pour rejoindre notre équipe. Vous serez en charge de développer et maintenir nos applications. Maîtrise de Java; Hadoop; Vue.js; React; TensorFlow; Machine Learning requise. Environnement technique moderne et innovant. Travail en mode Agile (Scrum/Kanban).",
      "competences_brut": "Java; Hadoop; Vue.js; React; TensorFlow; Machine Learning",
      "entreprise": "Oracle Maroc",
      "ville": "Rabat",
      "type_contrat": "Contrat à durée indéterminée",
      "experience_requise": "3 à 5 ans",
      "salaire_brut": null,
      "niveau_etudes": "Bac+3",
      "secteur": "Santé",
      "date_publication": "2023-04-02",
      "date_expiration": "2023-04-29",
      "nb_postes": 1,
      "teletravail": "",
      "langue_requise": [
        "Français"
      ]
    },
    {
      "id_offre": "RE-2023-03854",
      "source": "rekrute",
      "titre_poste": "Architecte Logiciel",
      "description": "Vous serez en charge de développer et maintenir nos applications. Travail en mode Agile (Scrum/Kanban). Environnement technique moderne et innovant. Nous recherchons un(e) Architecte Logiciel dynamique pour rejoindre notre équipe. Mission : participer aux projets stratégiques de l'entreprise.",
      "competences_brut": "Python / NLP / C# / JavaScript",
      "entreprise": "Microsoft Maroc",
      "ville": "Casablanca",
      "type_contrat": "CDD",
      "experience_requise": null,
      "salaire_brut": "À définir",
      "niveau_etudes": "Bac+3",
      "secteur": "Transport",
      "date_publication": "2023-04-07",
      "date_expiration": "2023-05-13",
      "nb_postes": 5,
      "teletravail": "Partiel",
      "langue_requise": [
        "Anglais",
        "Arabe"
      ]
    },
    {
      "id_offre": "RE-2023-03903",
      "source": "rekrute",
      "titre_poste": "Data Eng. Senior",
      "description": "Environnement technique moderne et innovant. Environnement technique : node. Travail en mode Agile (Scrum/Kanban). Nous recherchons un(e) Data Eng. Senior dynamique pour rejoindre notre équipe. Mission : participer aux projets stratégiques de l'entreprise. Vous serez en charge de développer et maintenir nos applications.",
      "competences_brut": "NumPy • Power BI • Django • Angular • TensorFlow",
      "entreprise": "Orange Maroc",
      "ville": "tanger",
      "type_contrat": "Contrat à durée indéterminée",
      "experience_requise": "Senior (7+ ans)",
      "salaire_brut": null,
      "niveau_etudes": "Bac+3",
      "secteur": "Banque / Finance",
      "date_publication": "2023-04-23",
      "date_expiration": "2023-05-19",
      "nb_postes": 1,
      "teletravail": "Télétravail complet",
      "langue_requise": []
    },
    {
      "id_offre": "RE-2023-03943",
      "source": "rekrute",
      "titre_poste": "Data Scientist",
      "description": "Nous recherchons un(e) Data Scientist dynamique pour rejoindre notre équipe. Environnement technique moderne et innovant. Mission : participer aux projets stratégiques de l'entreprise. Maîtrise de CD, Node.js requise. Vous serez en charge de développer et maintenir nos applications.",
      "competences_brut": "NLP / Tableau / Node.js / Python / Java / Docker / CI/CD / Power BI",
      "entreprise": "Wafasalaf",
      "ville": "Casablanca",
      "type_contrat": "CDD",
      "experience_requise": "3-5 ans",
      "salaire_brut": "Négociable",
      "niveau_etudes": "Ingénieur",
      "secteur": "Industrie",
      "date_publication": "2023-04-19",
      "date_expiration": "2023-05-20",
      "nb_postes": 1,
      "teletravail": "Non",
      "langue_requise": [
        "Français",
        "Anglais"
      ]
    },
    {
      "id_offre": "RE-2023-03981",
      "source": "rekrute",
      "titre_poste": "Analyste Data",
      "description": "Maîtrise de Pandas, PyTorch requise. Travail en mode Agile (Scrum/Kanban). Environnement technique moderne et innovant. Mission : participer aux projets stratégiques de l'entreprise.",
      "competences_brut": "R / PyTorch / Power BI / Pandas",
      "entreprise": "Inwi",
      "ville": "Tanger",
      "type_contrat": "Contrat à durée indéterminée",
      "experience_requise": "min 3 ans",
      "salaire_brut": "34K DH",
      "niveau_etudes": null,
      "secteur": "Banque / Finance",
      "date_publication": "2023-04-30",
      "date_expiration": "2023-05-31",
      "nb_postes": 4,
      "teletravail": "Non",
      "langue_requise": [
        "Anglais"
      ]
    },
    {
      "id_offre": "RE-2023-04001",
      "source": "rekrute",
      "titre_poste": "Machine Learning Engineer",
      "description": "Vous serez en charge de développer et maintenir nos applications. Environnement technique moderne et innovant. Mission : participer aux projets stratégiques de l'entreprise.",
      "competences_brut": "Spring Boot • Jenkins",
      "entreprise": "KPMG",
      "ville": "Casa",
      "type_contrat": "cdi",
      "experience_requise": "3-5 ans",
      "salaire_brut": "18K DH",
      "niveau_etudes": "Bac+4",
      "secteur": "Transport",
      "date_publication": "2023-04-07",
      "date_expiration": "2023-05-20",
      "nb_postes": 1,
      "teletravail": "Hybride",
      "langue_requise": [
        "Français",
        "Anglais"
      ]
    },
    {
      "id_offre": "RE-2023-04154",
      "source": "rekrute",
      "titre_poste": "Développeur Full Stack",
      "description": "Des connaissances en Git seraient un plus apprécié. Nous recherchons un(e) Développeur Full Stack dynamique pour rejoindre notre équipe. Vous serez en charge de développer et maintenir nos applications. Travail en mode Agile (Scrum/Kanban). Environnement technique moderne et innovant.",
      "competences_brut": "Power BI; AWS; JavaScript; Python; Azure; Angular",
      "entreprise": "Banque Populaire",
      "ville": "Casablanca",
      "type_contrat": "Contrat à durée indéterminée",
      "experience_requise": "Senior (7+ ans)",
      "salaire_brut": "22K-26K MAD",
      "niveau_etudes": "Bac+4",
      "secteur": "E-commerce",
      "date_publication": "2023-04-02",
      "date_expiration": "2023-05-06",
      "nb_postes": 5,
      "teletravail": "Télétravail complet",
      "langue_requise": [
        "Français",
        "Anglais"
      ]
    },
    {
      "id_offre": "RE-2023-04175",
      "source": "rekrute",
      "titre_poste": "Dev Full Stack",
      "description": "Maîtrise de React, Git requise. Nous recherchons un(e) Dev Full Stack dynamique pour rejoindre notre équipe. Vous serez en charge de développer et maintenir nos applications. Environnement technique moderne et innovant. Des connaissances en Scikit-learn seraient un plus apprécié. Mission : participer aux projets stratégiques de l'entreprise.",
      "competences_brut": "Terraform\nReact\nJava\nGit\nScala",
      "entreprise": "Solutions IT",
      "ville": "tanger",
      "type_contrat": "CDD",
      "experience_requise": "",
      "salaire_brut": "18K-20K MAD",
      "niveau_etudes": "Bac+3",
      "secteur": "Santé",
      "date_publication": "2023-04-11",
      "date_expiration": "2023-05-25",
      "nb_postes": 2,
      "teletravail": "Oui",
      "langue_requise": [
        "Anglais",
        "Arabe"
      ]
    },
    {
      "id_offre": "RE-2023-04197",
      "source": "rekrute",
      "titre_poste": "Data Eng.",
      "description": "Maîtrise de Angular, Kubernetes requise. Vous serez en charge de développer et maintenir nos applications. Environnement technique moderne et innovant. Mission : participer aux projets stratégiques de l'entreprise.",
      "competences_brut": "Kubernetes • Scala • Vue.js • Kafka • Java • Jenkins • Angular",
      "entreprise": "Microsoft Maroc",
      "ville": "CASABLANCA",
      "type_contrat": "Permanent",
      "experience_requise": "Moins de 1 an",
      "salaire_brut": null,
      "niveau_etudes": "Bac+2",
      "secteur": "Conseil",
      "date_publication": "2023-04-09",
      "date_expiration": "2023-05-10",
      "nb_postes": 5,
      "teletravail": "Oui",
      "langue_requise": [
        "Français"
      ]
    },
    {
      "id_offre": "RE-2023-04200",
      "source": "rekrute",
      "titre_poste": "Devops Engineer",
      "description": "Environnement technique moderne et innovant. Mission : participer aux projets stratégiques de l'entreprise. Travail en mode Agile (Scrum/Kanban). Nous recherchons un(e) Devops Engineer dynamique pour rejoindre notre équipe.",
      "competences_brut": "JavaScript, SQL, Kubernetes, Azure, GCP, Jenkins, R, Pandas",
      "entreprise": "Orange Maroc",
      "ville": "Rabat",
      "type_contrat": "Freelance",
      "experience_requise": "3-5 ans",
      "salaire_brut": "Selon profil",
      "niveau_etudes": "Licence",
      "secteur": "Banque / Finance",
      "date_publication": "2023-04-30",
      "date_expiration": "2023-06-13",
      "nb_postes": 2,
      "teletravail": "Télétravail complet",
      "langue_requise": []
    },
    {
      "id_offre": "RE-2023-04405",
      "source": "rekrute",
      "titre_poste": "Architecte Logiciel",
      "description": "Vous serez en charge de développer et maintenir nos applications. Environnement technique moderne et innovant. Travail en mode Agile (Scrum/Kanban). Mission : participer aux projets stratégiques de l'entreprise. Nous recherchons un(e) Architecte Logiciel dynamique pour rejoindre notre équipe.",
      "competences_brut": "Scikit-learn / Spring Boot / React",
      "entreprise": "Microsoft Maroc",
      "ville": "Marrakech",
      "type_contrat": "Stage",
      "experience_requise": "Débutant accepté",
      "salaire_brut": "4059-5479 EUR",
      "niveau_etudes": "Ingénieur",
      "secteur": "Informatique / Télécom",
      "date_publication": "2023-04-25",
      "date_expiration": "2023-05-30",
      "nb_postes": 3,
      "teletravail": "",
      "langue_requise": [
        "Français"
      ]
    },
    {
      "id_offre": "RE-2023-04450",
      "source": "rekrute",
      "titre_poste": "Data Engineer",
      "description": "Environnement technique : angular. Maîtrise de Deep Learning, R requise. Nous recherchons un(e) Data Engineer dynamique pour rejoindre notre équipe. Travail en mode Agile (Scrum/Kanban).",
      "competences_brut": "Spark, Deep Learning, Scikit-learn, R",
      "entreprise": "IBM Maroc",
      "ville": "Tanger",
      "type_contrat": "CDD",
      "experience_requise": "Moins de 1 an",
      "salaire_brut": "Négociable",
      "niveau_etudes": "Licence",
      "secteur": "Santé",
      "date_publication": "2023-04-08",
      "date_expiration": "2023-05-11",
      "nb_postes": 4,
      "teletravail": "Télétravail complet",
      "langue_requise": [
        "Français",
        "Anglais"
      ]
    },
    {
      "id_offre": "RE-2023-04593",
      "source": "rekrute",
      "titre_poste": "Back-end Engineer",
      "description": "Des connaissances en Looker seraient un plus apprécié. Nous recherchons un(e) Back-end Engineer dynamique pour rejoindre notre équipe. Vous serez en charge de développer et maintenir nos applications. Maîtrise de CD; Docker, Looker; Spark; CI requise. Environnement technique moderne et innovant. Travail en mode Agile (Scrum/Kanban).",
      "competences_brut": "Looker; Spark; CI/CD; Docker",
      "entreprise": "Informatique Services",
      "ville": "Marrakech",
      "type_contrat": "cdi",
      "experience_requise": "3-5 ans",
      "salaire_brut": "38K DH",
      "niveau_etudes": "Licence",
      "secteur": "Transport",
      "date_publication": "2023-04-08",
      "date_expiration": "2023-05-08",
      "nb_postes": 1,
      "teletravail": "",
      "langue_requise": [
        "Anglais"
      ]
    },
    {
      "id_offre": "RE-2023-04595",
      "source": "rekrute",
      "titre_poste": "Devops Engineer",
      "description": "Environnement technique moderne et innovant. Nous recherchons un(e) Devops Engineer dynamique pour rejoindre notre équipe. Travail en mode Agile (Scrum/Kanban). Vous serez en charge de développer et maintenir nos applications.",
      "competences_brut": "Git\nSpring Boot",
      "entreprise": "Inwi",
      "ville": "Casa",
      "type_contrat": "cdi",
      "experience_requise": "Senior (7+ ans)",
      "salaire_brut": "19178-45411 MAD",
      "niveau_etudes": null,
      "secteur": "Banque / Finance",
      "date_publication": "2023-04-12",
      "date_expiration": "2023-05-14",
      "nb_postes": 1,
      "teletravail": "Télétravail complet",
      "langue_requise": [
        "Anglais",
        "Arabe"
      ]
    },
    {
      "id_offre": "RE-2023-04627",
      "source": "rekrute",
      "titre_poste": "Devops Engineer",
      "description": "Nous recherchons un(e) Devops Engineer dynamique pour rejoindre notre équipe. Maîtrise de AWS, R requise. Mission : participer aux projets stratégiques de l'entreprise. Vous serez en charge de développer et maintenir nos applications. Des connaissances en Hadoop seraient un plus apprécié. Environnement technique moderne et innovant.",
      "competences_brut": "Scala\nAWS\nR",
      "entreprise": "Maroc Telecom",
      "ville": "Meknès",
      "type_contrat": "CDD",
      "experience_requise": "min 3 ans",
      "salaire_brut": "3352-7471 EUR",
      "niveau_etudes": "Licence",
      "secteur": "Énergie",
      "date_publication": "2023-04-24",
      "date_expiration": "2023-06-01",
      "nb_postes": 2,
      "teletravail": "Télétravail complet",
      "langue_requise": []
    },
    {
      "id_offre": "RE-2023-04654",
      "source": "rekrute",
      "titre_poste": "Scientifique des données Senior",
      "description": "Nous recherchons un(e) Scientifique des données Senior dynamique pour rejoindre notre équipe. Mission : participer aux projets stratégiques de l'entreprise. Maîtrise de AWS, Node.js requise. Environnement technique moderne et innovant. Vous serez en charge de développer et maintenir nos applications.",
      "competences_brut": "GCP\nSpark\nDeep Learning\nAirflow\nAWS\nNode.js\nTerraform",
      "entreprise": "Orange Maroc",
      "ville": "Tanger",
      "type_contrat": "Stage",
      "experience_requise": "",
      "salaire_brut": null,
      "niveau_etudes": "Bac+5",
      "secteur": "Énergie",
      "date_publication": "2023-04-18",
      "date_expiration": "2023-05-21",
      "nb_postes": 4,
      "teletravail": "Hybride",
      "langue_requise": [
        "Français",
        "Anglais"
      ]
    },
    {
      "id_offre": "RE-2023-04806",
      "source": "rekrute",
      "titre_poste": "Data Eng. Senior",
      "description": "Environnement technique : spring boot. Vous serez en charge de développer et maintenir nos applications. Nous recherchons un(e) Data Eng. Senior dynamique pour rejoindre notre équipe. Des connaissances en Node.js seraient un plus apprécié. Mission : participer aux projets stratégiques de l'entreprise. Maîtrise de Pandas, GCP requise.",
      "competences_brut": "Pandas\nGCP\nPower BI\nTerraform\nSpark\nScala\nMachine Learning",
      "entreprise": "Capgemini",
      "ville": "Meknès",
      "type_contrat": "Freelance",
      "experience_requise": "1-2 ans",
      "salaire_brut": "À définir",
      "niveau_etudes": "Bac+2",
      "secteur": "Transport",
      "date_publication": "2023-04-12",
      "date_expiration": "2023-05-20",
      "nb_postes": 2,
      "teletravail": "Partiel",
      "langue_requise": [
        "Français",
        "Anglais"
      ]
    },
    {
      "id_offre": "RE-2023-04859",
      "source": "rekrute",
      "titre_poste": "Analyste Data",
      "description": "Vous serez en charge de développer et maintenir nos applications. Environnement technique moderne et innovant. Travail en mode Agile (Scrum/Kanban). Des connaissances en Kubernetes seraient un plus apprécié.",
      "competences_brut": "Kubernetes; Deep Learning; R",
      "entreprise": "CloudMaroc",
      "ville": "TANGER",
      "type_contrat": "Freelance",
      "experience_requise": "min 3 ans",
      "salaire_brut": null,
      "niveau_etudes": "Master",
      "secteur": "Industrie",
      "date_publication": "2023-04-21",
      "date_expiration": "2023-05-20",
      "nb_postes": 4,
      "teletravail": "Non",
      "langue_requise": [
        "Français",
        "Anglais"
      ]
    },
    {
      "id_offre": "RE-2023-04885",
      "source": "rekrute",
      "titre_poste": "Chef de Projet IT",
      "description": "Mission : participer aux projets stratégiques de l'entreprise. Vous serez en charge de développer et maintenir nos applications. Travail en mode Agile (Scrum/Kanban). Maîtrise de Hadoop, Tableau requise.",
      "competences_brut": "Angular / Hadoop / Tableau / C# / SQL / Docker / Kafka / Terraform",
      "entreprise": "KPMG",
      "ville": "Meknès",
      "type_contrat": "CDI",
      "experience_requise": "5+ ans",
      "salaire_brut": "21847-45340 MAD",
      "niveau_etudes": null,
      "secteur": "Industrie",
      "date_publication": "2023-04-15",
      "date_expiration": "2023-04-05",
      "nb_postes": 1,
      "teletravail": "Oui",
      "langue_requise": [
        "Anglais"
      ]
    }
  ]
}